src/full_adder.sv
module full_adder (input logic a,b,cin,
                   output logic sum,cout);
                   



assign sum = a ^ b ^ cin;

assign cout = (a & b) ^ (a & cin) ^ (b & cin);

endmodule

src/add_subtract_unit.sv
module add_subtract_unit #(parameter WIDTH = 32) (
    input logic [WIDTH - 1:0] a, b,
    input logic  sub,
    output logic [WIDTH - 1:0] sum,
    output logic cout
);

logic [WIDTH - 1:0] inv_b;
logic [WIDTH:0] carry;


assign inv_b = b ^ {WIDTH{sub}};
assign carry[0] = sub;
assign cout = carry[WIDTH];

genvar i;
generate
    for (i = 0; i < WIDTH; i++) begin : adder_chain
        full_adder fa (
            .a(a[i]),
            .b(inv_b[i]),
            .cin (carry[i]),
            .sum(sum[i]),
            .cout(carry[i+1])
        );
    end

endgenerate
endmodule

tb/add_subtract_unit_tb.sv
module add_subtract_unit_tb;
localparam WIDTH = 32;

logic [WIDTH - 1:0] a , b, sum, exp_sum,exp_diff;
logic sub,cout;

add_subtract_unit #(.WIDTH(WIDTH)) dut(
    .a(a),
    .b(b),
    .sum(sum),
    .sub(sub),
    .cout(cout)
);

task check_add(); 
    exp_sum = a + b;
    if(exp_sum === sum)
        $display("PASS_ADD a = %h | b = %h | sub = %h | exp_sum = %h | sum = %h",a,b,sub,exp_sum,sum);
    else
        $error("FAIL_ADD a = %h | b = %h | sub = %h | exp_sum = %h | sum = %h",a,b,sub,exp_sum,sum);
endtask

task check_sub(); 
    exp_diff = a - b;
    if(exp_diff === sum)
        $display("PASS_SUB a = %h | b = %h | sub = %h | exp_diff = %h | sum = %h",a,b,sub,exp_diff,sum);
    else
        $error("FAIL_SUB a = %h | b = %h | sub = %h | exp_diff = %h | sum = %h",a,b,sub,exp_diff,sum);
endtask

initial begin
    $dumpfile("dump/add_subtract_unit_dump.vcd");
    $dumpvars(0, add_subtract_unit_tb);
    a = 32'h00000000; b = 32'h00000000; sub = 1'b0; #10; check_add();
    a = 32'hFFFFFFFF; b = 32'hFFFFFFFF; sub = 1'b0; #10; check_add();
    a = 32'hFFFFFFFF; b = 32'hFFFFFFFF; sub = 1'b0; #10; check_add();

    for(int i = 0; i < 50; i++) begin
        a = $urandom;
        b = $urandom;
        sub = 0;
        #10;
        check_add();
    end

    a = 32'h00000000; b = 32'h00000000; sub = 1'b1; #10; check_sub();
    a = 32'hFFFFFFFF; b = 32'hFFFFFFFF; sub = 1'b1; #10; check_sub();
    a = 32'hFFFFFFFF; b = 32'hFFFFFFFF; sub = 1'b1; #10; check_sub();

    for(int i = 0; i < 50; i++) begin
        a = $urandom;
        b = $urandom;
        sub = 1;
        #10;
        check_sub();
    end
end
endmodule

dump/add_subtract_unit_dump.vcd
$date
	Thu Jun 25 10:47:36 2026
$end
$version
	Icarus Verilog
$end
$timescale
	1s
$end
$scope module add_subtract_unit_tb $end
$var wire 32 ! sum [31:0] $end
$var wire 1 " cout $end
$var parameter 32 # WIDTH $end
$var reg 32 $ a [31:0] $end
$var reg 32 % b [31:0] $end
$var reg 32 & exp_diff [31:0] $end
$var reg 32 ' exp_sum [31:0] $end
$var reg 1 ( sub $end
$scope module dut $end
$var wire 32 ) a [31:0] $end
$var wire 32 * b [31:0] $end
$var wire 32 + inv_b [31:0] $end
$var wire 1 ( sub $end
$var wire 32 , sum [31:0] $end
$var wire 1 " cout $end
$var wire 33 - carry [32:0] $end
$var parameter 32 . WIDTH $end
$scope begin adder_chain[0] $end
$var parameter 2 / i $end
$scope module fa $end
$var wire 1 0 a $end
$var wire 1 1 b $end
$var wire 1 2 cin $end
$var wire 1 3 cout $end
$var wire 1 4 sum $end
$upscope $end
$upscope $end
$scope begin adder_chain[1] $end
$var parameter 2 5 i $end
$scope module fa $end
$var wire 1 6 a $end
$var wire 1 7 b $end
$var wire 1 8 cin $end
$var wire 1 9 cout $end
$var wire 1 : sum $end
$upscope $end
$upscope $end
$scope begin adder_chain[2] $end
$var parameter 3 ; i $end
$scope module fa $end
$var wire 1 < a $end
$var wire 1 = b $end
$var wire 1 > cin $end
$var wire 1 ? cout $end
$var wire 1 @ sum $end
$upscope $end
$upscope $end
$scope begin adder_chain[3] $end
$var parameter 3 A i $end
$scope module fa $end
$var wire 1 B a $end
$var wire 1 C b $end
$var wire 1 D cin $end
$var wire 1 E cout $end
$var wire 1 F sum $end
$upscope $end
$upscope $end
$scope begin adder_chain[4] $end
$var parameter 4 G i $end
$scope module fa $end
$var wire 1 H a $end
$var wire 1 I b $end
$var wire 1 J cin $end
$var wire 1 K cout $end
$var wire 1 L sum $end
$upscope $end
$upscope $end
$scope begin adder_chain[5] $end
$var parameter 4 M i $end
$scope module fa $end
$var wire 1 N a $end
$var wire 1 O b $end
$var wire 1 P cin $end
$var wire 1 Q cout $end
$var wire 1 R sum $end
$upscope $end
$upscope $end
$scope begin adder_chain[6] $end
$var parameter 4 S i $end
$scope module fa $end
$var wire 1 T a $end
$var wire 1 U b $end
$var wire 1 V cin $end
$var wire 1 W cout $end
$var wire 1 X sum $end
$upscope $end
$upscope $end
$scope begin adder_chain[7] $end
$var parameter 4 Y i $end
$scope module fa $end
$var wire 1 Z a $end
$var wire 1 [ b $end
$var wire 1 \ cin $end
$var wire 1 ] cout $end
$var wire 1 ^ sum $end
$upscope $end
$upscope $end
$scope begin adder_chain[8] $end
$var parameter 5 _ i $end
$scope module fa $end
$var wire 1 ` a $end
$var wire 1 a b $end
$var wire 1 b cin $end
$var wire 1 c cout $end
$var wire 1 d sum $end
$upscope $end
$upscope $end
$scope begin adder_chain[9] $end
$var parameter 5 e i $end
$scope module fa $end
$var wire 1 f a $end
$var wire 1 g b $end
$var wire 1 h cin $end
$var wire 1 i cout $end
$var wire 1 j sum $end
$upscope $end
$upscope $end
$scope begin adder_chain[10] $end
$var parameter 5 k i $end
$scope module fa $end
$var wire 1 l a $end
$var wire 1 m b $end
$var wire 1 n cin $end
$var wire 1 o cout $end
$var wire 1 p sum $end
$upscope $end
$upscope $end
$scope begin adder_chain[11] $end
$var parameter 5 q i $end
$scope module fa $end
$var wire 1 r a $end
$var wire 1 s b $end
$var wire 1 t cin $end
$var wire 1 u cout $end
$var wire 1 v sum $end
$upscope $end
$upscope $end
$scope begin adder_chain[12] $end
$var parameter 5 w i $end
$scope module fa $end
$var wire 1 x a $end
$var wire 1 y b $end
$var wire 1 z cin $end
$var wire 1 { cout $end
$var wire 1 | sum $end
$upscope $end
$upscope $end
$scope begin adder_chain[13] $end
$var parameter 5 } i $end
$scope module fa $end
$var wire 1 ~ a $end
$var wire 1 !" b $end
$var wire 1 "" cin $end
$var wire 1 #" cout $end
$var wire 1 $" sum $end
$upscope $end
$upscope $end
$scope begin adder_chain[14] $end
$var parameter 5 %" i $end
$scope module fa $end
$var wire 1 &" a $end
$var wire 1 '" b $end
$var wire 1 (" cin $end
$var wire 1 )" cout $end
$var wire 1 *" sum $end
$upscope $end
$upscope $end
$scope begin adder_chain[15] $end
$var parameter 5 +" i $end
$scope module fa $end
$var wire 1 ," a $end
$var wire 1 -" b $end
$var wire 1 ." cin $end
$var wire 1 /" cout $end
$var wire 1 0" sum $end
$upscope $end
$upscope $end
$scope begin adder_chain[16] $end
$var parameter 6 1" i $end
$scope module fa $end
$var wire 1 2" a $end
$var wire 1 3" b $end
$var wire 1 4" cin $end
$var wire 1 5" cout $end
$var wire 1 6" sum $end
$upscope $end
$upscope $end
$scope begin adder_chain[17] $end
$var parameter 6 7" i $end
$scope module fa $end
$var wire 1 8" a $end
$var wire 1 9" b $end
$var wire 1 :" cin $end
$var wire 1 ;" cout $end
$var wire 1 <" sum $end
$upscope $end
$upscope $end
$scope begin adder_chain[18] $end
$var parameter 6 =" i $end
$scope module fa $end
$var wire 1 >" a $end
$var wire 1 ?" b $end
$var wire 1 @" cin $end
$var wire 1 A" cout $end
$var wire 1 B" sum $end
$upscope $end
$upscope $end
$scope begin adder_chain[19] $end
$var parameter 6 C" i $end
$scope module fa $end
$var wire 1 D" a $end
$var wire 1 E" b $end
$var wire 1 F" cin $end
$var wire 1 G" cout $end
$var wire 1 H" sum $end
$upscope $end
$upscope $end
$scope begin adder_chain[20] $end
$var parameter 6 I" i $end
$scope module fa $end
$var wire 1 J" a $end
$var wire 1 K" b $end
$var wire 1 L" cin $end
$var wire 1 M" cout $end
$var wire 1 N" sum $end
$upscope $end
$upscope $end
$scope begin adder_chain[21] $end
$var parameter 6 O" i $end
$scope module fa $end
$var wire 1 P" a $end
$var wire 1 Q" b $end
$var wire 1 R" cin $end
$var wire 1 S" cout $end
$var wire 1 T" sum $end
$upscope $end
$upscope $end
$scope begin adder_chain[22] $end
$var parameter 6 U" i $end
$scope module fa $end
$var wire 1 V" a $end
$var wire 1 W" b $end
$var wire 1 X" cin $end
$var wire 1 Y" cout $end
$var wire 1 Z" sum $end
$upscope $end
$upscope $end
$scope begin adder_chain[23] $end
$var parameter 6 [" i $end
$scope module fa $end
$var wire 1 \" a $end
$var wire 1 ]" b $end
$var wire 1 ^" cin $end
$var wire 1 _" cout $end
$var wire 1 `" sum $end
$upscope $end
$upscope $end
$scope begin adder_chain[24] $end
$var parameter 6 a" i $end
$scope module fa $end
$var wire 1 b" a $end
$var wire 1 c" b $end
$var wire 1 d" cin $end
$var wire 1 e" cout $end
$var wire 1 f" sum $end
$upscope $end
$upscope $end
$scope begin adder_chain[25] $end
$var parameter 6 g" i $end
$scope module fa $end
$var wire 1 h" a $end
$var wire 1 i" b $end
$var wire 1 j" cin $end
$var wire 1 k" cout $end
$var wire 1 l" sum $end
$upscope $end
$upscope $end
$scope begin adder_chain[26] $end
$var parameter 6 m" i $end
$scope module fa $end
$var wire 1 n" a $end
$var wire 1 o" b $end
$var wire 1 p" cin $end
$var wire 1 q" cout $end
$var wire 1 r" sum $end
$upscope $end
$upscope $end
$scope begin adder_chain[27] $end
$var parameter 6 s" i $end
$scope module fa $end
$var wire 1 t" a $end
$var wire 1 u" b $end
$var wire 1 v" cin $end
$var wire 1 w" cout $end
$var wire 1 x" sum $end
$upscope $end
$upscope $end
$scope begin adder_chain[28] $end
$var parameter 6 y" i $end
$scope module fa $end
$var wire 1 z" a $end
$var wire 1 {" b $end
$var wire 1 |" cin $end
$var wire 1 }" cout $end
$var wire 1 ~" sum $end
$upscope $end
$upscope $end
$scope begin adder_chain[29] $end
$var parameter 6 !# i $end
$scope module fa $end
$var wire 1 "# a $end
$var wire 1 ## b $end
$var wire 1 $# cin $end
$var wire 1 %# cout $end
$var wire 1 &# sum $end
$upscope $end
$upscope $end
$scope begin adder_chain[30] $end
$var parameter 6 '# i $end
$scope module fa $end
$var wire 1 (# a $end
$var wire 1 )# b $end
$var wire 1 *# cin $end
$var wire 1 +# cout $end
$var wire 1 ,# sum $end
$upscope $end
$upscope $end
$scope begin adder_chain[31] $end
$var parameter 6 -# i $end
$scope module fa $end
$var wire 1 .# a $end
$var wire 1 /# b $end
$var wire 1 0# cin $end
$var wire 1 1# cout $end
$var wire 1 2# sum $end
$upscope $end
$upscope $end
$upscope $end
$scope begin $ivl_for_loop0 $end
$var integer 32 3# i [31:0] $end
$upscope $end
$scope begin $ivl_for_loop1 $end
$var integer 32 4# i [31:0] $end
$upscope $end
$scope task check_add $end
$upscope $end
$scope task check_sub $end
$upscope $end
$upscope $end
$enddefinitions $end
$comment Show the parameter values. $end
$dumpall
b11111 -#
b11110 '#
b11101 !#
b11100 y"
b11011 s"
b11010 m"
b11001 g"
b11000 a"
b10111 ["
b10110 U"
b10101 O"
b10100 I"
b10011 C"
b10010 ="
b10001 7"
b10000 1"
b1111 +"
b1110 %"
b1101 }
b1100 w
b1011 q
b1010 k
b1001 e
b1000 _
b111 Y
b110 S
b101 M
b100 G
b11 A
b10 ;
b1 5
b0 /
b100000 .
b100000 #
$end
#0
$dumpvars
b0 4#
b0 3#
02#
01#
00#
0/#
0.#
0,#
0+#
0*#
0)#
0(#
0&#
0%#
0$#
0##
0"#
0~"
0}"
0|"
0{"
0z"
0x"
0w"
0v"
0u"
0t"
0r"
0q"
0p"
0o"
0n"
0l"
0k"
0j"
0i"
0h"
0f"
0e"
0d"
0c"
0b"
0`"
0_"
0^"
0]"
0\"
0Z"
0Y"
0X"
0W"
0V"
0T"
0S"
0R"
0Q"
0P"
0N"
0M"
0L"
0K"
0J"
0H"
0G"
0F"
0E"
0D"
0B"
0A"
0@"
0?"
0>"
0<"
0;"
0:"
09"
08"
06"
05"
04"
03"
02"
00"
0/"
0."
0-"
0,"
0*"
0)"
0("
0'"
0&"
0$"
0#"
0""
0!"
0~
0|
0{
0z
0y
0x
0v
0u
0t
0s
0r
0p
0o
0n
0m
0l
0j
0i
0h
0g
0f
0d
0c
0b
0a
0`
0^
0]
0\
0[
0Z
0X
0W
0V
0U
0T
0R
0Q
0P
0O
0N
0L
0K
0J
0I
0H
0F
0E
0D
0C
0B
0@
0?
0>
0=
0<
0:
09
08
07
06
04
03
02
01
00
b0 -
b0 ,
b0 +
b0 *
b0 )
0(
bx '
bx &
b0 %
b0 $
0"
b0 !
$end
#10
18
1>
1D
1J
1P
1V
1\
1b
1h
1n
1t
1z
1""
1("
1."
14"
1:"
1@"
1F"
1L"
1R"
1X"
1^"
1d"
1j"
1p"
1v"
1|"
1$#
1*#
10#
1"
13
19
1?
1E
1K
1Q
1W
1]
1c
1i
1o
1u
1{
1#"
1)"
1/"
15"
1;"
1A"
1G"
1M"
1S"
1Y"
1_"
1e"
1k"
1q"
1w"
1}"
1%#
1+#
b111111111111111111111111111111110 -
11#
04
1:
1@
1F
1L
1R
1X
1^
1d
1j
1p
1v
1|
1$"
1*"
10"
16"
1<"
1B"
1H"
1N"
1T"
1Z"
1`"
1f"
1l"
1r"
1x"
1~"
1&#
1,#
b11111111111111111111111111111110 !
b11111111111111111111111111111110 ,
12#
11
17
1=
1C
1I
1O
1U
1[
1a
1g
1m
1s
1y
1!"
1'"
1-"
13"
19"
1?"
1E"
1K"
1Q"
1W"
1]"
1c"
1i"
1o"
1u"
1{"
1##
1)#
1/#
b11111111111111111111111111111111 +
10
16
1<
1B
1H
1N
1T
1Z
1`
1f
1l
1r
1x
1~
1&"
1,"
12"
18"
1>"
1D"
1J"
1P"
1V"
1\"
1b"
1h"
1n"
1t"
1z"
1"#
1(#
1.#
b11111111111111111111111111111111 %
b11111111111111111111111111111111 *
b11111111111111111111111111111111 $
b11111111111111111111111111111111 )
b0 '
#20
b11111111111111111111111111111110 '
#30
1""
1{
1|
1z
1u
1t
1o
0p
0b
0n
1."
1:"
0L"
0d"
00#
0]
0i
1)"
15"
0G"
0_"
0+#
06"
0>
0D
0J
0P
0V
0\
0h
1("
04"
0@"
0F"
0R"
0X"
0^"
0j"
0p"
0v"
0|"
0$#
0*#
0"
08
09
1@
0?
0E
0K
1R
0Q
0W
1d
0c
0$"
1#"
0/"
0;"
1B"
0A"
1N"
0M"
0S"
0Y"
0e"
1l"
0k"
0q"
0w"
1~"
0}"
0%#
12#
01#
b101111100000000000 -
03
14
0:
0F
0L
0X
1^
1j
0v
0*"
10"
1<"
1H"
0T"
0Z"
1`"
0f"
0r"
0x"
0&#
b11010010100111101001001110100101 !
b11010010100111101001001110100101 ,
1,#
07
0=
0C
0I
0O
0U
0a
0!"
0-"
09"
0?"
0K"
0Q"
0W"
0c"
0i"
0o"
0u"
0{"
0##
0/#
b1000000100010010101111010000001 +
00
06
0B
0H
0T
0Z
0f
0r
0&"
0,"
08"
0D"
0P"
0V"
0\"
0b"
0n"
0t"
0"#
0(#
b1000000100010010101111010000001 %
b1000000100010010101111010000001 *
b10010010000101010011010100100100 $
b10010010000101010011010100100100 )
#40
1""
1>
1t
1."
1j"
1{
19
1o
1)"
1e"
0|
1p
0<"
0z
18
1n
0("
14"
0:"
1d"
0:
1X
0^
1v
0u
0H"
1T"
1Z"
0f"
1&#
0,#
13
1i
0#"
1/"
05"
b11000000011010110000000110 -
1_"
04
1@
1F
1R
0d
0j
1$"
0*"
00"
16"
1N"
0`"
1l"
1r"
1~"
b110110011101010010110001101100 !
b110110011101010010110001101100 ,
02#
17
1O
1U
0[
0s
03"
0E"
1K"
1Q"
1W"
1c"
1{"
1##
0)#
b110001111100000101011001100011 +
10
0<
1B
0N
0`
1f
0~
1&"
1,"
02"
0J"
1\"
0h"
1n"
0z"
0.#
b110001111100000101011001100011 %
b110001111100000101011001100011 *
b100100001001101011000001001 $
b100100001001101011000001001 )
b1 3#
b11010010100111101001001110100101 '
#50
1F"
1A"
1d"
1_"
1""
14"
1@"
1`"
1{
1/"
1;"
1^"
1L
1|
1x"
1Y"
1D
1J
1h
1n
1z
1."
1:"
1L"
1p"
1v"
1"
0Z"
0>
1?
1E
1c
1i
0t
1u
1)"
15"
1G"
0j"
1k"
1q"
11#
1("
1R"
1X"
1:
09
1F
0R
0X
1^
0j
0o
0*"
0<"
1f"
0e"
1r"
0~"
0&#
1,#
1#"
1M"
b100001101111111111111011000011010 -
1S"
0@
0d
1p
0v
0$"
00"
16"
0B"
1H"
1N"
0T"
0l"
b1001101100110010001010010011010 !
b1001101100110010001010010011010 ,
02#
07
1=
1C
0O
0U
1[
1a
0g
0m
1s
0'"
1-"
13"
19"
1?"
1E"
0Q"
0c"
1i"
1o"
0{"
0##
1)#
1/#
b11000110110111111001100110001101 +
1<
1`
0l
1r
1~
0,"
12"
0>"
1D"
1J"
1P"
1h"
1.#
b11000110110111111001100110001101 %
b11000110110111111001100110001101 *
b10000110101110010111101100001101 $
b10000110101110010111101100001101 )
b10 3#
b110110011101010010110001101100 '
#60
1F"
0\
1A"
0*#
0W
0B"
0%#
1@"
0X"
1;"
0S"
0V
0$#
0Q
0:"
0R"
0}"
0n
0""
0."
05"
0M"
0i
0{
0)"
08
0D
0p"
03
0>
0?
0J
0P
04"
0L"
0^"
0d"
0j"
0k"
0v"
0|"
0h
0t
0z
0("
0"
14
1:
09
1@
0E
1L
0K
0^
0/"
0G"
0Y"
1`"
0_"
1f"
0e"
1l"
0q"
1x"
0w"
0,#
0c
0o
0u
0#"
b11000000000000000000 -
01#
0F
1R
1X
0d
1j
1p
0v
1|
0$"
1*"
10"
16"
0<"
1H"
1N"
1T"
1Z"
0r"
1~"
1&#
b111011111110011101011001110111 !
b111011111110011101011001110111 ,
02#
01
17
0=
0C
1I
0[
0a
1g
0s
1'"
0-"
0E"
1Q"
0W"
0]"
1c"
0i"
0o"
1u"
0)#
0/#
b1001001101110101001000010010 +
0B
1N
1T
0`
0f
1l
0r
0x
0~
0&"
1,"
02"
18"
0D"
0J"
0P"
1V"
0n"
1z"
1"#
0.#
b1001001101110101001000010010 %
b1001001101110101001000010010 *
b110010110000101000010001100101 $
b110010110000101000010001100101 )
b11 3#
b1001101100110010001010010011010 '
#70
1H"
1z
1F"
1u
1A"
0B"
1t
1@"
1o
1;"
18
1h
14"
1^"
1d"
1"
1<"
13
1c
1/"
1Y"
1_"
11#
1n
1."
1:"
1R"
1X"
04
1:
1F
0L
0v
1|
10"
1Z"
1`"
1f"
1r"
0x"
1i
1)"
15"
1M"
b100000001111011111001111000000010 -
1S"
1@
0R
0X
0d
0j
0p
1$"
0*"
16"
0N"
0T"
1l"
0~"
0&#
b111110010111011000000001110 !
b111110010111011000000001110 ,
02#
11
07
1=
1C
0I
1a
0g
1m
1s
0y
1-"
0Q"
1W"
1]"
0c"
1i"
1o"
0u"
1/#
b10000110110101111100110100001101 +
0<
0N
0T
1`
1f
0l
1~
1&"
12"
1J"
1P"
0h"
0z"
0"#
1.#
b10000110110101111100110100001101 %
b10000110110101111100110100001101 *
b10000000111100111110001100000001 $
b10000000111100111110001100000001 )
b100 3#
b111011111110011101011001110111 '
#80
1:"
15"
16"
14"
1/"
10"
1."
1^
1,#
0z
1)"
1\
1*#
0u
0*"
1W
1%#
1v
0("
0X"
1F"
0d"
1J
0t
0#"
0S"
1v"
1A"
0_"
1E
0o
1q"
1P
1V
0B"
1|"
1$#
0F
1p
1$"
1T"
0r"
1K
1Q
1@"
1L"
0^"
1w"
1}"
08
0>
1D
0n
0""
0R"
0j"
1p"
0<"
1;"
0H"
1G"
0Y"
03
09
1?
0i
0{
0M"
0e"
b101111100000111111000001011111000 -
1k"
14
1:
0@
1L
1R
0X
1j
1|
1N"
0Z"
1`"
1f"
0l"
1x"
1~"
b1011001101100011011111010110011 !
b1011001101100011011111010110011 ,
0&#
1I
1O
09"
1E"
0K"
0W"
1u"
1{"
b10011110100011011100110100111101 +
00
16
1<
1H
1N
1T
0f
1x
0J"
0V"
0\"
1b"
1h"
1t"
1z"
1"#
b10011110100011011100110100111101 %
b10011110100011011100110100111101 *
b10111011001000111111000101110110 $
b10111011001000111111000101110110 )
b101 3#
b111110010111011000000001110 '
#90
1:"
15"
14"
1/"
1."
1^"
1)"
1L"
1Y"
1*"
1G"
0\
1h
1("
0*#
1"
0H"
0W
1c
1#"
0%#
11#
1F"
1X"
1d
12#
1A"
1S"
1X
1b
1n
1""
1&#
10#
0P
0V
1]
1i
1{
0|"
0$#
1+#
08
1t
0@"
1R"
1d"
0K
1R
0Q
1v
0|
0w"
1~"
0}"
03
1o
0;"
1M"
b110001101111110111110111100011000 -
1_"
14
0:
1F
1L
0^
1j
1p
0$"
00"
06"
1<"
0B"
0N"
0T"
0Z"
0`"
1f"
1r"
1x"
b10111101000000100100111101111001 !
b10111101000000100100111101111001 ,
0,#
01
0I
0O
1[
1g
0s
1y
1!"
1Q"
0]"
0u"
0{"
1)#
b11000110001011011111011110001100 +
10
06
1B
0H
1Z
1f
1l
0~
0,"
02"
08"
1>"
1J"
0P"
1V"
1\"
0b"
1n"
0t"
1(#
b11000110001011011111011110001100 %
b11000110001011011111011110001100 *
b11110110110101000101011111101101 $
b11110110110101000101011111101101 )
b110 3#
b1011001101100011011111010110011 '
#100
1d"
1_"
0`"
1^"
1Y"
1b
0Z"
10#
0V
1$#
1]
0t
1:"
1F"
1X"
1+#
0Q
1("
1}"
1^
0o
15"
1A"
1S"
1,#
1#"
1\
1B"
1*#
1R
0~"
0J
1W
1h
0n
1."
14"
1@"
1L"
1R"
1j"
1v"
1%#
1"
0D
0P
0z
0""
1p"
1|"
1:
1F
0E
0X
0d
1c
0i
0*"
1)"
1/"
0<"
1;"
1G"
1N"
1M"
0f"
1e"
0r"
1q"
1&#
02#
11#
0?
0K
0u
0{
1k"
b111111111111111111100001110000000 -
1w"
1@
1L
1j
1p
1v
0|
0$"
00"
16"
0H"
1T"
0l"
b1100000001101010000111010111111 !
b1100000001101010000111010111111 ,
0x"
17
0C
1U
0a
0g
0y
0'"
0-"
19"
0E"
1K"
1c"
0o"
1##
0/#
b1100011001101110010010011000110 +
0<
1H
0f
0l
1r
0x
1~
1,"
12"
1D"
1P"
0h"
1t"
b1100011001101110010010011000110 %
b1100011001101110010010011000110 *
b11111100111111011110100111111001 $
b11111100111111011110100111111001 )
b111 3#
b10111101000000100100111101111001 '
#110
1j"
1e"
0f"
1d"
1_"
1@"
1;"
0`"
1b
1^"
1]
1:"
1Y"
1v"
10#
0J
0."
1R"
0$#
0^
15"
1q"
1+#
0E
0)"
1M"
0}"
0\
16"
0Z"
0,#
0N"
0W
0n
14"
1F"
1X"
1p"
0*#
0D
0h
0t
0("
0L"
0|"
0"
1X
1j
0i
1|
00"
1/"
0B"
1A"
0T"
1S"
1k"
1&#
0%#
0?
0c
0o
0#"
0G"
0w"
b10001111111011110000000100000000 -
01#
1@
1F
0L
1R
1d
1p
0v
0$"
1*"
1<"
1H"
0l"
0r"
1x"
1~"
b10111000000010110101011101101111 !
b10111000000010110101011101101111 ,
12#
0=
1C
1O
0U
1g
0m
1y
0!"
1'"
1-"
0?"
0Q"
0i"
1o"
1{"
0##
b1010101000100111101001010101010 +
1<
0B
0H
0N
0`
1l
0r
0~
0&"
18"
0D"
1h"
0n"
0t"
0z"
0.#
b1010101000100111101001010101010 %
b1010101000100111101001010101010 *
b1100010111101111000010011000101 $
b1100010111101111000010011000101 )
b1000 3#
b1100000001101010000111010111111 '
#120
1F"
1^"
1A"
1Y"
1v
1>
0B"
1t
1X"
19
1@"
1j"
1o
1S"
0:
1;"
1e"
18
1D
1\
1b
1("
14"
1<"
0f"
1*#
10#
0p
0T"
13
1?
1W
1]
1#"
1/"
1:"
1d"
1p"
0v"
0|"
1%#
1+#
1V
1h
1n
1""
1."
1L"
1R"
1$#
1"
04
1@
1F
1L
1X
0^
00"
06"
15"
1`"
1_"
1l"
1k"
1r"
0q"
1x"
0w"
1&#
0,#
1Q
1c
1i
1{
1)"
1G"
1M"
1}"
b111100111111111111110111111001110 -
11#
0R
0d
1j
0|
1$"
1*"
0H"
0N"
0Z"
0~"
b101110100000100110101001011100 !
b101110100000100110101001011100 ,
02#
11
1=
0C
1I
1U
0[
1!"
0-"
03"
1W"
1]"
1i"
0o"
1u"
1##
0)#
b111011110100100111001001110111 +
1N
1`
1f
1x
1~
1&"
1D"
0J"
0V"
1z"
1.#
b111011110100100111001001110111 %
b111011110100100111001001110111 *
b11110010101011111111011111100101 $
b11110010101011111111011111100101 )
b1001 3#
b10111000000010110101011101101111 '
#130
1t
1o
1p"
1k"
0p
1n
1j"
1i
1e"
0j
0h
0L"
1d"
0"
1D
0c
0G"
1_"
01#
1?
0b
1""
1."
0F"
1^"
00#
1>
0]
1{
1)"
0A"
1Y"
0+#
19
1|
0*"
0Z"
1J
0\
1z
0("
14"
0@"
0R"
1X"
1v"
0*#
08
1P
0V
0:"
1|"
0$#
0F
1E
0W
0v
1u
0#"
10"
1/"
1<"
0;"
0M"
0T"
1S"
0r"
1q"
0%#
03
1K
0Q
05"
1w"
b11111110000011011110000111100 -
0}"
14
0:
0@
0L
1R
0X
1^
1d
1$"
16"
1B"
1H"
1N"
0`"
1f"
0l"
0x"
1~"
0&#
1,#
b11010001000111111011000110100001 !
b11010001000111111011000110100001 ,
12#
1C
0I
0O
0U
1[
1a
1s
0!"
1-"
09"
1?"
1E"
0K"
1Q"
1o"
0u"
0{"
0##
1)#
1/#
b11000111111011001101101110001111 +
00
16
0<
1H
0N
0T
0Z
0`
0~
02"
0>"
0D"
1J"
0\"
1b"
0h"
1t"
0z"
0"#
0(#
0.#
b11000111111011001101101110001111 %
b11000111111011001101101110001111 *
b1001001100101101011000010010 $
b1001001100101101011000010010 )
b1010 3#
b101110100000100110101001011100 '
#140
1|"
1w"
0x"
1v"
1q"
1^"
0r"
1Y"
1p"
16"
0Z"
1k"
14"
1X"
0l"
1""
1/"
1S"
1j"
1t
1{
1T"
1e"
1o
1\
1."
1R"
0f"
1*#
1W
1z
1)"
1M"
0d"
1%#
1V
1b
1h
1n
1("
1$#
10#
1"
04
1u
0*"
0H"
0N"
1`"
0_"
1Q
1]
1c
1i
1#"
1}"
1+#
b111111110111000011111111111111100 -
11#
0R
1X
1^
0d
0j
0p
0v
0|
0$"
00"
1<"
0~"
1&#
1,#
b1100000101001110000000011000000 !
b1100000101001110000000011000000 ,
02#
01
1U
0a
1m
0s
0'"
19"
0E"
1K"
0]"
1##
0/#
b1100111011101101001011011001110 +
1N
1T
1Z
1`
0f
0l
1r
0x
1~
0,"
08"
1z"
1"#
1(#
1.#
b1100111011101101001011011001110 %
b1100111011101101001011011001110 *
b11111001001100000110100111110010 $
b11111001001100000110100111110010 )
b1011 3#
b11010001000111111011000110100001 '
#150
1b
10#
1]
1+#
1^
1,#
1\
1*#
1W
1t
1%#
0X
1o
0&#
1("
0V
0p
0$#
1#"
0^"
0D
0Q
1n
0p"
0}"
0Y"
0?
1i
0k"
0$"
06"
1Z"
1@
1R
1l"
1~"
0J
1z
1""
1."
04"
0X"
0d"
0v"
0>
0P
0h
0R"
0j"
0|"
0"
14
0E
1v
1u
1{
1*"
1)"
10"
0/"
0B"
1H"
0S"
1`"
0_"
0q"
09
0K
0c
0M"
0e"
0w"
b11000000000000001111110110000000 -
01#
0:
1F
0L
1d
0j
0|
0N"
0T"
0f"
1r"
0x"
b11010110110010101100100110101101 !
b11010110110010101100100110101101 ,
12#
11
07
0C
1s
0y
1'"
0-"
0?"
1E"
0K"
0Q"
1]"
0c"
0o"
b1100010110010100100111011000101 +
06
1B
0H
0`
1f
1x
0J"
0P"
0b"
1n"
0t"
0.#
b1100010110010100100111011000101 %
b1100010110010100100111011000101 *
b1110100000000000111101011101000 $
b1110100000000000111101011101000 )
b1100 3#
b1100000101001110000000011000000 '
#160
1T"
1V
1b
1$#
10#
1R"
0f"
1Q
1]
1z
1}"
1+#
0("
1M"
0d"
1u
0#"
0_"
1J
1P
1\
0v
00"
1v"
1|"
1*#
1`"
1E
1K
1W
0t
0."
1q"
1w"
1%#
1D
1h
0n
0""
1L"
0^"
1p"
1"
1F
0X
0p
0o
1*"
0)"
1B"
1r"
0&#
1?
1c
0i
0{
1G"
0Y"
1k"
b111111100001100000001001111111000 -
11#
0@
1L
0R
0^
0d
1j
1|
1$"
0H"
0N"
1Z"
0l"
1x"
0~"
0,#
b1100111001100111001000011001 !
b1100111001100111001000011001 ,
02#
1C
1I
1O
0U
0g
0m
1!"
0'"
1?"
0W"
1o"
1u"
1{"
0##
b1011110100011100010100010111101 +
1<
1H
0N
0Z
1`
0f
0x
0~
1D"
1J"
1V"
1h"
1t"
0z"
0(#
1.#
b1011110100011100010100010111101 %
b1011110100011100010100010111101 *
b10101110010110000100100101011100 $
b10101110010110000100100101011100 )
b1101 3#
b11010110110010101100100110101101 '
