src/full_adder.sv
module full_adder (input logic a,b,cin,
                   output logic sum,cout);
                   



assign sum = a ^ b ^ cin;

assign cout = (a & b) ^ (a & cin) ^ (b & cin);

endmodule

src/ripple_carry_adder.sv
module ripple_carry_adder #(parameter WIDTH = 32) (
    input logic [WIDTH - 1:0] a, b,
    input logic cin,
    output logic [WIDTH - 1:0] sum,
    output logic cout
);

logic [WIDTH:0] carry;
assign carry[0] = cin;
assign cout = carry[WIDTH];

genvar i;
generate
    for (i = 0; i < WIDTH; i++) begin : adder_chain
        full_adder fa (
            .a(a[i]),
            .b(b[i]),
            .cin (carry[i]),
            .sum(sum[i]),
            .cout(carry[i+1])
        );
    end

endgenerate
endmodule

tb/ripple_carry_adder_tb.sv
module ripple_carry_adder_tb;
localparam WIDTH = 32;

logic [WIDTH - 1:0] a ,b, sum, exp_sum;
logic cin, cout,exp_cout;

ripple_carry_adder #(.WIDTH(WIDTH)) dut(a,b,cin,sum,cout);

integer fh;
integer scan_result;
integer pass_count, fail_count, test_num;

initial begin

  $dumpfile("dump/ripple_dump.vcd");
  $dumpvars(0, ripple_carry_adder_tb);

  // rest of code
    pass_count = 0;
    fail_count = 0;
    test_num = 0;

    fh = $fopen("tb/ripple_carry_adder_tb.tv","r");
    if (fh==0)begin
        $display("ERROR: could not open vector file");
        $finish;
    end
    begin : read_loop
        string line;
        while (!$feof(fh)) begin
            if ($fgets(line, fh) == 0) break;
            if (line.substr(0,1) == "//") continue;
            scan_result = $sscanf(line, "%b %b %b %b %b", a, b, cin, exp_sum, exp_cout);
            if (scan_result != 5) continue;
            #10;

            test_num++;
            if(sum !== exp_sum || cout !== exp_cout) begin
                $display("FAIL test %0d | a=%b b=%b cin=%b | got sum=%b cout=%b | expected sum=%b cout=%b",
                            test_num,a,b,cin,sum,cout,exp_sum,exp_cout);
                fail_count++;
            end else begin
                $display("PASS test %0d | a=%b b=%b cin=%b = %b",
                            test_num,a,b,cin,sum);
                pass_count++;
            end
        end
    end : read_loop
    $fclose(fh);
    $display("--- %0d passed, %0d failed ---", pass_count, fail_count);
    $finish;
end

endmodule

dump/ripple_dump.vcd
$date
	Tue Jun 09 12:06:09 2026
$end
$version
	Icarus Verilog
$end
$timescale
	1s
$end
$scope module ripple_carry_adder_tb $end
$var wire 32 ! sum [31:0] $end
$var wire 1 " cout $end
$var parameter 32 # WIDTH $end
$var reg 32 $ a [31:0] $end
$var reg 32 % b [31:0] $end
$var reg 1 & cin $end
$var reg 1 ' exp_cout $end
$var reg 32 ( exp_sum [31:0] $end
$var integer 32 ) fail_count [31:0] $end
$var integer 32 * fh [31:0] $end
$var integer 32 + pass_count [31:0] $end
$var integer 32 , scan_result [31:0] $end
$var integer 32 - test_num [31:0] $end
$scope module dut $end
$var wire 32 . a [31:0] $end
$var wire 32 / b [31:0] $end
$var wire 1 & cin $end
$var wire 32 0 sum [31:0] $end
$var wire 1 " cout $end
$var wire 33 1 carry [32:0] $end
$var parameter 32 2 WIDTH $end
$scope begin adder_chain[0] $end
$var parameter 2 3 i $end
$scope module fa $end
$var wire 1 4 a $end
$var wire 1 5 b $end
$var wire 1 6 cin $end
$var wire 1 7 cout $end
$var wire 1 8 sum $end
$upscope $end
$upscope $end
$scope begin adder_chain[1] $end
$var parameter 2 9 i $end
$scope module fa $end
$var wire 1 : a $end
$var wire 1 ; b $end
$var wire 1 < cin $end
$var wire 1 = cout $end
$var wire 1 > sum $end
$upscope $end
$upscope $end
$scope begin adder_chain[2] $end
$var parameter 3 ? i $end
$scope module fa $end
$var wire 1 @ a $end
$var wire 1 A b $end
$var wire 1 B cin $end
$var wire 1 C cout $end
$var wire 1 D sum $end
$upscope $end
$upscope $end
$scope begin adder_chain[3] $end
$var parameter 3 E i $end
$scope module fa $end
$var wire 1 F a $end
$var wire 1 G b $end
$var wire 1 H cin $end
$var wire 1 I cout $end
$var wire 1 J sum $end
$upscope $end
$upscope $end
$scope begin adder_chain[4] $end
$var parameter 4 K i $end
$scope module fa $end
$var wire 1 L a $end
$var wire 1 M b $end
$var wire 1 N cin $end
$var wire 1 O cout $end
$var wire 1 P sum $end
$upscope $end
$upscope $end
$scope begin adder_chain[5] $end
$var parameter 4 Q i $end
$scope module fa $end
$var wire 1 R a $end
$var wire 1 S b $end
$var wire 1 T cin $end
$var wire 1 U cout $end
$var wire 1 V sum $end
$upscope $end
$upscope $end
$scope begin adder_chain[6] $end
$var parameter 4 W i $end
$scope module fa $end
$var wire 1 X a $end
$var wire 1 Y b $end
$var wire 1 Z cin $end
$var wire 1 [ cout $end
$var wire 1 \ sum $end
$upscope $end
$upscope $end
$scope begin adder_chain[7] $end
$var parameter 4 ] i $end
$scope module fa $end
$var wire 1 ^ a $end
$var wire 1 _ b $end
$var wire 1 ` cin $end
$var wire 1 a cout $end
$var wire 1 b sum $end
$upscope $end
$upscope $end
$scope begin adder_chain[8] $end
$var parameter 5 c i $end
$scope module fa $end
$var wire 1 d a $end
$var wire 1 e b $end
$var wire 1 f cin $end
$var wire 1 g cout $end
$var wire 1 h sum $end
$upscope $end
$upscope $end
$scope begin adder_chain[9] $end
$var parameter 5 i i $end
$scope module fa $end
$var wire 1 j a $end
$var wire 1 k b $end
$var wire 1 l cin $end
$var wire 1 m cout $end
$var wire 1 n sum $end
$upscope $end
$upscope $end
$scope begin adder_chain[10] $end
$var parameter 5 o i $end
$scope module fa $end
$var wire 1 p a $end
$var wire 1 q b $end
$var wire 1 r cin $end
$var wire 1 s cout $end
$var wire 1 t sum $end
$upscope $end
$upscope $end
$scope begin adder_chain[11] $end
$var parameter 5 u i $end
$scope module fa $end
$var wire 1 v a $end
$var wire 1 w b $end
$var wire 1 x cin $end
$var wire 1 y cout $end
$var wire 1 z sum $end
$upscope $end
$upscope $end
$scope begin adder_chain[12] $end
$var parameter 5 { i $end
$scope module fa $end
$var wire 1 | a $end
$var wire 1 } b $end
$var wire 1 ~ cin $end
$var wire 1 !" cout $end
$var wire 1 "" sum $end
$upscope $end
$upscope $end
$scope begin adder_chain[13] $end
$var parameter 5 #" i $end
$scope module fa $end
$var wire 1 $" a $end
$var wire 1 %" b $end
$var wire 1 &" cin $end
$var wire 1 '" cout $end
$var wire 1 (" sum $end
$upscope $end
$upscope $end
$scope begin adder_chain[14] $end
$var parameter 5 )" i $end
$scope module fa $end
$var wire 1 *" a $end
$var wire 1 +" b $end
$var wire 1 ," cin $end
$var wire 1 -" cout $end
$var wire 1 ." sum $end
$upscope $end
$upscope $end
$scope begin adder_chain[15] $end
$var parameter 5 /" i $end
$scope module fa $end
$var wire 1 0" a $end
$var wire 1 1" b $end
$var wire 1 2" cin $end
$var wire 1 3" cout $end
$var wire 1 4" sum $end
$upscope $end
$upscope $end
$scope begin adder_chain[16] $end
$var parameter 6 5" i $end
$scope module fa $end
$var wire 1 6" a $end
$var wire 1 7" b $end
$var wire 1 8" cin $end
$var wire 1 9" cout $end
$var wire 1 :" sum $end
$upscope $end
$upscope $end
$scope begin adder_chain[17] $end
$var parameter 6 ;" i $end
$scope module fa $end
$var wire 1 <" a $end
$var wire 1 =" b $end
$var wire 1 >" cin $end
$var wire 1 ?" cout $end
$var wire 1 @" sum $end
$upscope $end
$upscope $end
$scope begin adder_chain[18] $end
$var parameter 6 A" i $end
$scope module fa $end
$var wire 1 B" a $end
$var wire 1 C" b $end
$var wire 1 D" cin $end
$var wire 1 E" cout $end
$var wire 1 F" sum $end
$upscope $end
$upscope $end
$scope begin adder_chain[19] $end
$var parameter 6 G" i $end
$scope module fa $end
$var wire 1 H" a $end
$var wire 1 I" b $end
$var wire 1 J" cin $end
$var wire 1 K" cout $end
$var wire 1 L" sum $end
$upscope $end
$upscope $end
$scope begin adder_chain[20] $end
$var parameter 6 M" i $end
$scope module fa $end
$var wire 1 N" a $end
$var wire 1 O" b $end
$var wire 1 P" cin $end
$var wire 1 Q" cout $end
$var wire 1 R" sum $end
$upscope $end
$upscope $end
$scope begin adder_chain[21] $end
$var parameter 6 S" i $end
$scope module fa $end
$var wire 1 T" a $end
$var wire 1 U" b $end
$var wire 1 V" cin $end
$var wire 1 W" cout $end
$var wire 1 X" sum $end
$upscope $end
$upscope $end
$scope begin adder_chain[22] $end
$var parameter 6 Y" i $end
$scope module fa $end
$var wire 1 Z" a $end
$var wire 1 [" b $end
$var wire 1 \" cin $end
$var wire 1 ]" cout $end
$var wire 1 ^" sum $end
$upscope $end
$upscope $end
$scope begin adder_chain[23] $end
$var parameter 6 _" i $end
$scope module fa $end
$var wire 1 `" a $end
$var wire 1 a" b $end
$var wire 1 b" cin $end
$var wire 1 c" cout $end
$var wire 1 d" sum $end
$upscope $end
$upscope $end
$scope begin adder_chain[24] $end
$var parameter 6 e" i $end
$scope module fa $end
$var wire 1 f" a $end
$var wire 1 g" b $end
$var wire 1 h" cin $end
$var wire 1 i" cout $end
$var wire 1 j" sum $end
$upscope $end
$upscope $end
$scope begin adder_chain[25] $end
$var parameter 6 k" i $end
$scope module fa $end
$var wire 1 l" a $end
$var wire 1 m" b $end
$var wire 1 n" cin $end
$var wire 1 o" cout $end
$var wire 1 p" sum $end
$upscope $end
$upscope $end
$scope begin adder_chain[26] $end
$var parameter 6 q" i $end
$scope module fa $end
$var wire 1 r" a $end
$var wire 1 s" b $end
$var wire 1 t" cin $end
$var wire 1 u" cout $end
$var wire 1 v" sum $end
$upscope $end
$upscope $end
$scope begin adder_chain[27] $end
$var parameter 6 w" i $end
$scope module fa $end
$var wire 1 x" a $end
$var wire 1 y" b $end
$var wire 1 z" cin $end
$var wire 1 {" cout $end
$var wire 1 |" sum $end
$upscope $end
$upscope $end
$scope begin adder_chain[28] $end
$var parameter 6 }" i $end
$scope module fa $end
$var wire 1 ~" a $end
$var wire 1 !# b $end
$var wire 1 "# cin $end
$var wire 1 ## cout $end
$var wire 1 $# sum $end
$upscope $end
$upscope $end
$scope begin adder_chain[29] $end
$var parameter 6 %# i $end
$scope module fa $end
$var wire 1 &# a $end
$var wire 1 '# b $end
$var wire 1 (# cin $end
$var wire 1 )# cout $end
$var wire 1 *# sum $end
$upscope $end
$upscope $end
$scope begin adder_chain[30] $end
$var parameter 6 +# i $end
$scope module fa $end
$var wire 1 ,# a $end
$var wire 1 -# b $end
$var wire 1 .# cin $end
$var wire 1 /# cout $end
$var wire 1 0# sum $end
$upscope $end
$upscope $end
$scope begin adder_chain[31] $end
$var parameter 6 1# i $end
$scope module fa $end
$var wire 1 2# a $end
$var wire 1 3# b $end
$var wire 1 4# cin $end
$var wire 1 5# cout $end
$var wire 1 6# sum $end
$upscope $end
$upscope $end
$upscope $end
$upscope $end
$enddefinitions $end
$comment Show the parameter values. $end
$dumpall
b11111 1#
b11110 +#
b11101 %#
b11100 }"
b11011 w"
b11010 q"
b11001 k"
b11000 e"
b10111 _"
b10110 Y"
b10101 S"
b10100 M"
b10011 G"
b10010 A"
b10001 ;"
b10000 5"
b1111 /"
b1110 )"
b1101 #"
b1100 {
b1011 u
b1010 o
b1001 i
b1000 c
b111 ]
b110 W
b101 Q
b100 K
b11 E
b10 ?
b1 9
b0 3
b100000 2
b100000 #
$end
#0
$dumpvars
x6#
x5#
x4#
x3#
x2#
x0#
x/#
x.#
x-#
x,#
x*#
x)#
x(#
x'#
x&#
x$#
x##
x"#
x!#
x~"
x|"
x{"
xz"
xy"
xx"
xv"
xu"
xt"
xs"
xr"
xp"
xo"
xn"
xm"
xl"
xj"
xi"
xh"
xg"
xf"
xd"
xc"
xb"
xa"
x`"
x^"
x]"
x\"
x["
xZ"
xX"
xW"
xV"
xU"
xT"
xR"
xQ"
xP"
xO"
xN"
xL"
xK"
xJ"
xI"
xH"
xF"
xE"
xD"
xC"
xB"
x@"
x?"
x>"
x="
x<"
x:"
x9"
x8"
x7"
x6"
x4"
x3"
x2"
x1"
x0"
x."
x-"
x,"
x+"
x*"
x("
x'"
x&"
x%"
x$"
x""
x!"
x~
x}
x|
xz
xy
xx
xw
xv
xt
xs
xr
xq
xp
xn
xm
xl
xk
xj
xh
xg
xf
xe
xd
xb
xa
x`
x_
x^
x\
x[
xZ
xY
xX
xV
xU
xT
xS
xR
xP
xO
xN
xM
xL
xJ
xI
xH
xG
xF
xD
xC
xB
xA
x@
x>
x=
x<
x;
x:
x8
x7
x6
x5
x4
bx 1
bx 0
bx /
bx .
b0 -
b0 ,
b0 +
b10000000000000000000000000000011 *
b0 )
bx (
x'
x&
bx %
bx $
x"
bx !
$end
#10
b1 +
b1 -
#20
b10 +
b10 -
#30
b11 +
b11 -
#40
b100 +
b100 -
#50
b101 +
b101 -
#60
b110 +
b110 -
#70
b111 +
b111 -
#80
b1000 +
b1000 -
#90
b1001 +
b1001 -
#100
b1010 +
b1010 -
#110
b1011 +
b1011 -
#120
b1100 +
b1100 -
#130
b1101 +
b1101 -
#140
b1110 +
b1110 -
#150
b1111 +
b1111 -
#160
b10000 +
b10000 -
#170
b10001 +
b10001 -
#180
b10010 +
b10010 -
#190
b10011 +
b10011 -
#200
b10100 +
b10100 -
#210
b10101 +
b10101 -
#220
b10110 +
b10110 -
#230
b10111 +
b10111 -
#240
b11000 +
b11000 -
#250
b11001 +
b11001 -
#260
b11010 +
b11010 -
#270
b11011 +
b11011 -
#280
b11100 +
b11100 -
#290
b11101 +
b11101 -
#300
b11110 +
b11110 -
#310
b11111 +
b11111 -
#320
b100000 +
b100000 -
#330
b100001 +
b100001 -
#340
b100010 +
b100010 -
#350
b100011 +
b100011 -
#360
b100100 +
b100100 -
#370
b100101 +
b100101 -
#380
b100110 +
b100110 -
#390
b100111 +
b100111 -
#400
b101000 +
b101000 -
#410
b101001 +
b101001 -
#420
b101010 +
b101010 -
#430
b101011 +
b101011 -
#440
b101100 +
b101100 -
#450
b101101 +
b101101 -
#460
b101110 +
b101110 -
#470
b101111 +
b101111 -
#480
b110000 +
b110000 -
#490
b110001 +
b110001 -
#500
b110010 +
b110010 -
#510
b110011 +
b110011 -
#520
b110100 +
b110100 -
#530
b110101 +
b110101 -
#540
b110110 +
b110110 -
#550
b110111 +
b110111 -
#560
b111000 +
b111000 -
#570
b111001 +
b111001 -
#580
b111010 +
b111010 -
#590
b111011 +
b111011 -
#600
b111100 +
b111100 -
#610
b111101 +
b111101 -
#620
b111110 +
b111110 -
#630
b111111 +
b111111 -
#640
b1000000 +
b1000000 -
#650
b1000001 +
b1000001 -
#660
b1000010 +
b1000010 -
#670
b1000011 +
b1000011 -
#680
b1000100 +
b1000100 -
#690
b1000101 +
b1000101 -
#700
b1000110 +
b1000110 -
#710
b1000111 +
b1000111 -
#720
b1001000 +
b1001000 -
#730
b1001001 +
b1001001 -
#740
b1001010 +
b1001010 -
#750
b1001011 +
b1001011 -
#760
b1001100 +
b1001100 -
#770
b1001101 +
b1001101 -
#780
b1001110 +
b1001110 -
#790
b1001111 +
b1001111 -
#800
b1010000 +
b1010000 -
#810
b1010001 +
b1010001 -
#820
b1010010 +
b1010010 -
#830
b1010011 +
b1010011 -
#840
b1010100 +
b1010100 -
#850
b1010101 +
b1010101 -
#860
b1010110 +
b1010110 -
#870
b1010111 +
b1010111 -
#880
b1011000 +
b1011000 -
#890
b1011001 +
b1011001 -
#900
b1011010 +
b1011010 -
#910
b1011011 +
b1011011 -
#920
b1011100 +
b1011100 -
#930
b1011101 +
b1011101 -
#940
b1011110 +
b1011110 -
#950
b1011111 +
b1011111 -
#960
b1100000 +
b1100000 -
#970
b1100001 +
b1100001 -
#980
b1100010 +
b1100010 -
#990
b1100011 +
b1100011 -
#1000
b1100100 +
b1100100 -
#1010
b1100101 +
b1100101 -
#1020
b1100110 +
b1100110 -
#1030
b1100111 +
b1100111 -
#1040
b1101000 +
b1101000 -
#1050
b1101001 +
b1101001 -
#1060
b1101010 +
b1101010 -
#1070
b1101011 +
b1101011 -
#1080
b1101100 +
b1101100 -
#1090
b1101101 +
b1101101 -
#1100
b1101110 +
b1101110 -
#1110
b1101111 +
b1101111 -
#1120
b1110000 +
b1110000 -
#1130
b1110001 +
b1110001 -
#1140
b1110010 +
b1110010 -
#1150
b1110011 +
b1110011 -
#1160
b1110100 +
b1110100 -
#1170
b1110101 +
b1110101 -
#1180
b1110110 +
b1110110 -
#1190
b1110111 +
b1110111 -
#1200
b1111000 +
b1111000 -
#1210
b1111001 +
b1111001 -
#1220
b1111010 +
b1111010 -
#1230
b1111011 +
b1111011 -
#1240
b1111100 +
b1111100 -
#1250
b1111101 +
b1111101 -
#1260
b1111110 +
b1111110 -
#1270
b1111111 +
b1111111 -
#1280
b10000000 +
b10000000 -
#1290
b10000001 +
b10000001 -
#1300
b10000010 +
b10000010 -
#1310
b10000011 +
b10000011 -
#1320
b10000100 +
b10000100 -
#1330
b10000101 +
b10000101 -
#1340
b10000110 +
b10000110 -
#1350
b10000111 +
b10000111 -
#1360
b10001000 +
b10001000 -
#1370
b10001001 +
b10001001 -
#1380
b10001010 +
b10001010 -
#1390
b10001011 +
b10001011 -
#1400
b10001100 +
b10001100 -
#1410
b10001101 +
b10001101 -
#1420
b10001110 +
b10001110 -
#1430
b10001111 +
b10001111 -
#1440
b10010000 +
b10010000 -
#1450
b10010001 +
b10010001 -
#1460
b10010010 +
b10010010 -
#1470
b10010011 +
b10010011 -
#1480
b10010100 +
b10010100 -
#1490
b10010101 +
b10010101 -
#1500
b10010110 +
b10010110 -
#1510
b10010111 +
b10010111 -
#1520
b10011000 +
b10011000 -
#1530
b10011001 +
b10011001 -
#1540
b10011010 +
b10011010 -
#1550
b10011011 +
b10011011 -
#1560
b10011100 +
b10011100 -
#1570
b10011101 +
b10011101 -
#1580
b10011110 +
b10011110 -
#1590
b10011111 +
b10011111 -
#1600
b10100000 +
b10100000 -
#1610
b10100001 +
b10100001 -
#1620
b10100010 +
b10100010 -
#1630
b10100011 +
b10100011 -
#1640
b10100100 +
b10100100 -
#1650
b10100101 +
b10100101 -
#1660
b10100110 +
b10100110 -
#1670
b10100111 +
b10100111 -
#1680
b10101000 +
b10101000 -
#1690
b10101001 +
b10101001 -
#1700
b10101010 +
b10101010 -
#1710
b10101011 +
b10101011 -
#1720
b10101100 +
b10101100 -
#1730
b10101101 +
b10101101 -
#1740
b10101110 +
b10101110 -
#1750
b10101111 +
b10101111 -
#1760
b10110000 +
b10110000 -
#1770
b10110001 +
b10110001 -
#1780
b10110010 +
b10110010 -
#1790
b10110011 +
b10110011 -
#1800
b10110100 +
b10110100 -
#1810
b10110101 +
b10110101 -
#1820
b10110110 +
b10110110 -
#1830
b10110111 +
b10110111 -
#1840
b10111000 +
b10111000 -
#1850
b10111001 +
b10111001 -
#1860
b10111010 +
b10111010 -
#1870
b10111011 +
b10111011 -
#1880
b10111100 +
b10111100 -
#1890
b10111101 +
b10111101 -
#1900
b10111110 +
b10111110 -
#1910
b10111111 +
b10111111 -
#1920
b11000000 +
b11000000 -
#1930
b11000001 +
b11000001 -
#1940
b11000010 +
b11000010 -
#1950
b11000011 +
b11000011 -
#1960
b11000100 +
b11000100 -
#1970
b11000101 +
b11000101 -
#1980
b11000110 +
b11000110 -
#1990
b11000111 +
b11000111 -
#2000
b11001000 +
b11001000 -
#2010
b11001001 +
b11001001 -
#2020
b11001010 +
b11001010 -
#2030
b11001011 +
b11001011 -
#2040
b11001100 +
b11001100 -
#2050
b11001101 +
b11001101 -
#2060
b11001110 +
b11001110 -
#2070
b11001111 +
b11001111 -
#2080
b11010000 +
b11010000 -
#2090
b11010001 +
b11010001 -
#2100
b11010010 +
b11010010 -
#2110
b11010011 +
b11010011 -
#2120
b11010100 +
b11010100 -
#2130
b11010101 +
b11010101 -
#2140
b11010110 +
b11010110 -
#2150
b11010111 +
b11010111 -
#2160
b11011000 +
b11011000 -
#2170
b11011001 +
b11011001 -
#2180
b11011010 +
b11011010 -
#2190
b11011011 +
b11011011 -
#2200
b11011100 +
b11011100 -
#2210
b11011101 +
b11011101 -
#2220
b11011110 +
b11011110 -
#2230
b11011111 +
b11011111 -
#2240
b11100000 +
b11100000 -
#2250
b11100001 +
b11100001 -
#2260
b11100010 +
b11100010 -
#2270
b11100011 +
b11100011 -
#2280
b11100100 +
b11100100 -
#2290
b11100101 +
b11100101 -
#2300
b11100110 +
b11100110 -
#2310
b11100111 +
b11100111 -
#2320
b11101000 +
b11101000 -
#2330
b11101001 +
b11101001 -
#2340
b11101010 +
b11101010 -
#2350
b11101011 +
b11101011 -
#2360
b11101100 +
b11101100 -
#2370
b11101101 +
b11101101 -
#2380
b11101110 +
b11101110 -
#2390
b11101111 +
b11101111 -
#2400
b11110000 +
b11110000 -
#2410
b11110001 +
b11110001 -
#2420
b11110010 +
b11110010 -
#2430
b11110011 +
b11110011 -
#2440
b11110100 +
b11110100 -
#2450
b11110101 +
b11110101 -
#2460
b11110110 +
b11110110 -
#2470
b11110111 +
b11110111 -
#2480
b11111000 +
b11111000 -
#2490
b11111001 +
b11111001 -
#2500
b11111010 +
b11111010 -
#2510
b11111011 +
b11111011 -
#2520
b11111100 +
b11111100 -
#2530
b11111101 +
b11111101 -
#2540
b11111110 +
b11111110 -
#2550
b11111111 +
b11111111 -
#2560
b100000000 +
b100000000 -
#2570
b100000001 +
b100000001 -
#2580
b100000010 +
b100000010 -
#2590
b100000011 +
b100000011 -
#2600
b100000100 +
b100000100 -
#2610
b100000101 +
b100000101 -
#2620
b100000110 +
b100000110 -
#2630
b100000111 +
b100000111 -
#2640
b100001000 +
b100001000 -
#2650
b100001001 +
b100001001 -
#2660
b100001010 +
b100001010 -
#2670
b100001011 +
b100001011 -
#2680
b100001100 +
b100001100 -
#2690
b100001101 +
b100001101 -
#2700
b100001110 +
b100001110 -
#2710
b100001111 +
b100001111 -
#2720
b100010000 +
b100010000 -
#2730
b100010001 +
b100010001 -
#2740
b100010010 +
b100010010 -
#2750
b100010011 +
b100010011 -
#2760
b100010100 +
b100010100 -
#2770
b100010101 +
b100010101 -
#2780
b100010110 +
b100010110 -
#2790
b100010111 +
b100010111 -
#2800
b100011000 +
b100011000 -
#2810
b100011001 +
b100011001 -
#2820
b100011010 +
b100011010 -
#2830
b100011011 +
b100011011 -
#2840
b100011100 +
b100011100 -
#2850
b100011101 +
b100011101 -
#2860
b100011110 +
b100011110 -
#2870
b100011111 +
b100011111 -
#2880
b100100000 +
b100100000 -
#2890
b100100001 +
b100100001 -
#2900
b100100010 +
b100100010 -
#2910
b100100011 +
b100100011 -
#2920
b100100100 +
b100100100 -
#2930
b100100101 +
b100100101 -
#2940
b100100110 +
b100100110 -
#2950
b100100111 +
b100100111 -
#2960
b100101000 +
b100101000 -
#2970
b100101001 +
b100101001 -
#2980
b100101010 +
b100101010 -
#2990
b100101011 +
b100101011 -
#3000
b100101100 +
b100101100 -
#3010
b100101101 +
b100101101 -
#3020
b100101110 +
b100101110 -
#3030
b100101111 +
b100101111 -
#3040
b100110000 +
b100110000 -
#3050
b100110001 +
b100110001 -
#3060
b100110010 +
b100110010 -
#3070
b100110011 +
b100110011 -
#3080
b100110100 +
b100110100 -
#3090
b100110101 +
b100110101 -
#3100
b100110110 +
b100110110 -
#3110
b100110111 +
b100110111 -
#3120
b100111000 +
b100111000 -
#3130
b100111001 +
b100111001 -
#3140
b100111010 +
b100111010 -
#3150
b100111011 +
b100111011 -
#3160
b100111100 +
b100111100 -
#3170
b100111101 +
b100111101 -
#3180
b100111110 +
b100111110 -
#3190
b100111111 +
b100111111 -
#3200
b101000000 +
b101000000 -
#3210
b101000001 +
b101000001 -
#3220
b101000010 +
b101000010 -
#3230
b101000011 +
b101000011 -
#3240
b101000100 +
b101000100 -
#3250
b101000101 +
b101000101 -
#3260
b101000110 +
b101000110 -
#3270
b101000111 +
b101000111 -
#3280
b101001000 +
b101001000 -
#3290
b101001001 +
b101001001 -
#3300
b101001010 +
b101001010 -
#3310
b101001011 +
b101001011 -
#3320
b101001100 +
b101001100 -
#3330
b101001101 +
b101001101 -
#3340
b101001110 +
b101001110 -
#3350
b101001111 +
b101001111 -
#3360
b101010000 +
b101010000 -
#3370
b101010001 +
b101010001 -
#3380
b101010010 +
b101010010 -
#3390
b101010011 +
b101010011 -
#3400
b101010100 +
b101010100 -
#3410
b101010101 +
b101010101 -
#3420
b101010110 +
b101010110 -
#3430
b101010111 +
b101010111 -
#3440
b101011000 +
b101011000 -
#3450
b101011001 +
b101011001 -
#3460
b101011010 +
b101011010 -
#3470
b101011011 +
b101011011 -
#3480
b101011100 +
b101011100 -
#3490
b101011101 +
b101011101 -
#3500
b101011110 +
b101011110 -
#3510
b101011111 +
b101011111 -
#3520
b101100000 +
b101100000 -
#3530
b101100001 +
b101100001 -
#3540
b101100010 +
b101100010 -
#3550
b101100011 +
b101100011 -
#3560
b101100100 +
b101100100 -
#3570
b101100101 +
b101100101 -
#3580
b101100110 +
b101100110 -
#3590
b101100111 +
b101100111 -
#3600
b101101000 +
b101101000 -
#3610
b101101001 +
b101101001 -
#3620
b101101010 +
b101101010 -
#3630
b101101011 +
b101101011 -
#3640
b101101100 +
b101101100 -
#3650
b101101101 +
b101101101 -
#3660
b101101110 +
b101101110 -
#3670
b101101111 +
b101101111 -
#3680
b101110000 +
b101110000 -
#3690
b101110001 +
b101110001 -
#3700
b101110010 +
b101110010 -
#3710
b101110011 +
b101110011 -
#3720
b101110100 +
b101110100 -
#3730
b101110101 +
b101110101 -
#3740
b101110110 +
b101110110 -
#3750
b101110111 +
b101110111 -
#3760
b101111000 +
b101111000 -
#3770
b101111001 +
b101111001 -
#3780
b101111010 +
b101111010 -
#3790
b101111011 +
b101111011 -
#3800
b101111100 +
b101111100 -
#3810
b101111101 +
b101111101 -
#3820
b101111110 +
b101111110 -
#3830
b101111111 +
b101111111 -
#3840
b110000000 +
b110000000 -
#3850
b110000001 +
b110000001 -
#3860
b110000010 +
b110000010 -
#3870
b110000011 +
b110000011 -
#3880
b110000100 +
b110000100 -
#3890
b110000101 +
b110000101 -
#3900
b110000110 +
b110000110 -
#3910
b110000111 +
b110000111 -
#3920
b110001000 +
b110001000 -
#3930
b110001001 +
b110001001 -
#3940
b110001010 +
b110001010 -
#3950
b110001011 +
b110001011 -
#3960
b110001100 +
b110001100 -
#3970
b110001101 +
b110001101 -
#3980
b110001110 +
b110001110 -
#3990
b110001111 +
b110001111 -
#4000
b110010000 +
b110010000 -
#4010
b110010001 +
b110010001 -
#4020
b110010010 +
b110010010 -
#4030
b110010011 +
b110010011 -
#4040
b110010100 +
b110010100 -
#4050
b110010101 +
b110010101 -
#4060
b110010110 +
b110010110 -
#4070
b110010111 +
b110010111 -
#4080
b110011000 +
b110011000 -
#4090
b110011001 +
b110011001 -
#4100
b110011010 +
b110011010 -
#4110
b110011011 +
b110011011 -
#4120
b110011100 +
b110011100 -
#4130
b110011101 +
b110011101 -
#4140
b110011110 +
b110011110 -
#4150
b110011111 +
b110011111 -
#4160
b110100000 +
b110100000 -
#4170
b110100001 +
b110100001 -
#4180
b110100010 +
b110100010 -
#4190
b110100011 +
b110100011 -
#4200
b110100100 +
b110100100 -
#4210
b110100101 +
b110100101 -
#4220
b110100110 +
b110100110 -
#4230
b110100111 +
b110100111 -
#4240
b110101000 +
b110101000 -
#4250
b110101001 +
b110101001 -
#4260
b110101010 +
b110101010 -
#4270
b110101011 +
b110101011 -
#4280
b110101100 +
b110101100 -
#4290
b110101101 +
b110101101 -
#4300
b110101110 +
b110101110 -
#4310
b110101111 +
b110101111 -
#4320
b110110000 +
b110110000 -
#4330
b110110001 +
b110110001 -
#4340
b110110010 +
b110110010 -
#4350
b110110011 +
b110110011 -
#4360
b110110100 +
b110110100 -
#4370
b110110101 +
b110110101 -
#4380
b110110110 +
b110110110 -
#4390
b110110111 +
b110110111 -
#4400
b110111000 +
b110111000 -
#4410
b110111001 +
b110111001 -
#4420
b110111010 +
b110111010 -
#4430
b110111011 +
b110111011 -
#4440
b110111100 +
b110111100 -
#4450
b110111101 +
b110111101 -
#4460
b110111110 +
b110111110 -
#4470
b110111111 +
b110111111 -
#4480
b111000000 +
b111000000 -
#4490
b111000001 +
b111000001 -
#4500
b111000010 +
b111000010 -
#4510
b111000011 +
b111000011 -
#4520
b111000100 +
b111000100 -
#4530
b111000101 +
b111000101 -
#4540
b111000110 +
b111000110 -
#4550
b111000111 +
b111000111 -
#4560
b111001000 +
b111001000 -
#4570
b111001001 +
b111001001 -
#4580
b111001010 +
b111001010 -
#4590
b111001011 +
b111001011 -
#4600
b111001100 +
b111001100 -
#4610
b111001101 +
b111001101 -
#4620
b111001110 +
b111001110 -
#4630
b111001111 +
b111001111 -
#4640
b111010000 +
b111010000 -
#4650
b111010001 +
b111010001 -
#4660
b111010010 +
b111010010 -
#4670
b111010011 +
b111010011 -
#4680
b111010100 +
b111010100 -
#4690
b111010101 +
b111010101 -
#4700
b111010110 +
b111010110 -
#4710
b111010111 +
b111010111 -
#4720
b111011000 +
b111011000 -
#4730
b111011001 +
b111011001 -
#4740
b111011010 +
b111011010 -
#4750
b111011011 +
b111011011 -
#4760
b111011100 +
b111011100 -
#4770
b111011101 +
b111011101 -
#4780
b111011110 +
b111011110 -
#4790
b111011111 +
b111011111 -
#4800
b111100000 +
b111100000 -
#4810
b111100001 +
b111100001 -
#4820
b111100010 +
b111100010 -
#4830
b111100011 +
b111100011 -
#4840
b111100100 +
b111100100 -
#4850
b111100101 +
b111100101 -
#4860
b111100110 +
b111100110 -
#4870
b111100111 +
b111100111 -
#4880
b111101000 +
b111101000 -
#4890
b111101001 +
b111101001 -
#4900
b111101010 +
b111101010 -
#4910
b111101011 +
b111101011 -
#4920
b111101100 +
b111101100 -
#4930
b111101101 +
b111101101 -
#4940
b111101110 +
b111101110 -
#4950
b111101111 +
b111101111 -
#4960
b111110000 +
b111110000 -
#4970
b111110001 +
b111110001 -
#4980
b111110010 +
b111110010 -
