src/full_adder.sv
module full_adder (input logic a,b,cin,
                   output logic sum,cout);
                   



assign sum = a ^ b ^ cin;

assign cout = (a & b) ^ (a & cin) ^ (b & cin);

endmodule

src/ripple_carry_adder.sv
module ripple_carry_adder #(parameter WIDTH = 32) (
    input logic [WIDTH - 1:0] a, b,
    input logic cin,
    output logic [WIDTH - 1:0] sum,
    output logic cout
);

logic [WIDTH:0] carry;
assign carry[0] = cin;
assign cout = carry[WIDTH];

genvar i;
generate
    for (i = 0; i < WIDTH; i++) begin : adder_chain
        full_adder fa (
            .a(a[i]),
            .b(b[i]),
            .cin (carry[i]),
            .sum(sum[i]),
            .cout(carry[i+1])
        );
    end

endgenerate
endmodule

tb/ripple_carry_adder_tb.sv
module ripple_carry_adder_tb;
localparam WIDTH = 32;

logic [WIDTH - 1:0] a ,b, sum;
logic [WIDTH:0] exp_sum;
logic cin, cout;

ripple_carry_adder #(.WIDTH(WIDTH)) dut(
    .a(a),
    .b(b),
    .sum(sum),
    .cout(cout),
    .cin(cin)
    );

task check();
    exp_sum = a + b + cin;
    #5;
    if ({cout,sum} !== exp_sum)
        $error("FAIL a:%h | b:%h | cin:%b | sum:%h | exp_sum: %h", a,b,cin,sum,exp_sum[31:0]);
    else
        $display("PASS a:%h | b:%h | cin:%b | sum:%h | exp_sum: %h", a,b,cin,sum,exp_sum[31:0]);
endtask

initial begin
    $dumpfile("dump/ripple_dump.vcd");
    $dumpvars(0, ripple_carry_adder_tb);
    a = 32'h00000000; b = 32'h00000000; cin = 1'b0; #10; check();
    a = 32'hFFFFFFFF; b = 32'hFFFFFFFF; cin = 1'b0; #10; check();
    a = 32'hFFFFFFFF; b = 32'hFFFFFFFF; cin = 1'b1; #10; check();

    for(int i = 0; i < 50; i++) begin
        a = $urandom;
        b = $urandom;
        cin = $urandom_range(0, 1);
        #10;
        check();
    end
end
endmodule

dump/ripple_dump.vcd
$date
	Tue Jun 23 11:54:47 2026
$end
$version
	Icarus Verilog
$end
$timescale
	1s
$end
$scope module ripple_carry_adder_tb $end
$var wire 32 ! sum [31:0] $end
$var wire 1 " cout $end
$var parameter 32 # WIDTH $end
$var reg 32 $ a [31:0] $end
$var reg 32 % b [31:0] $end
$var reg 1 & cin $end
$var reg 33 ' exp_sum [32:0] $end
$scope module dut $end
$var wire 32 ( a [31:0] $end
$var wire 32 ) b [31:0] $end
$var wire 1 & cin $end
$var wire 32 * sum [31:0] $end
$var wire 1 " cout $end
$var wire 33 + carry [32:0] $end
$var parameter 32 , WIDTH $end
$scope begin adder_chain[0] $end
$var parameter 2 - i $end
$scope module fa $end
$var wire 1 . a $end
$var wire 1 / b $end
$var wire 1 0 cin $end
$var wire 1 1 cout $end
$var wire 1 2 sum $end
$upscope $end
$upscope $end
$scope begin adder_chain[1] $end
$var parameter 2 3 i $end
$scope module fa $end
$var wire 1 4 a $end
$var wire 1 5 b $end
$var wire 1 6 cin $end
$var wire 1 7 cout $end
$var wire 1 8 sum $end
$upscope $end
$upscope $end
$scope begin adder_chain[2] $end
$var parameter 3 9 i $end
$scope module fa $end
$var wire 1 : a $end
$var wire 1 ; b $end
$var wire 1 < cin $end
$var wire 1 = cout $end
$var wire 1 > sum $end
$upscope $end
$upscope $end
$scope begin adder_chain[3] $end
$var parameter 3 ? i $end
$scope module fa $end
$var wire 1 @ a $end
$var wire 1 A b $end
$var wire 1 B cin $end
$var wire 1 C cout $end
$var wire 1 D sum $end
$upscope $end
$upscope $end
$scope begin adder_chain[4] $end
$var parameter 4 E i $end
$scope module fa $end
$var wire 1 F a $end
$var wire 1 G b $end
$var wire 1 H cin $end
$var wire 1 I cout $end
$var wire 1 J sum $end
$upscope $end
$upscope $end
$scope begin adder_chain[5] $end
$var parameter 4 K i $end
$scope module fa $end
$var wire 1 L a $end
$var wire 1 M b $end
$var wire 1 N cin $end
$var wire 1 O cout $end
$var wire 1 P sum $end
$upscope $end
$upscope $end
$scope begin adder_chain[6] $end
$var parameter 4 Q i $end
$scope module fa $end
$var wire 1 R a $end
$var wire 1 S b $end
$var wire 1 T cin $end
$var wire 1 U cout $end
$var wire 1 V sum $end
$upscope $end
$upscope $end
$scope begin adder_chain[7] $end
$var parameter 4 W i $end
$scope module fa $end
$var wire 1 X a $end
$var wire 1 Y b $end
$var wire 1 Z cin $end
$var wire 1 [ cout $end
$var wire 1 \ sum $end
$upscope $end
$upscope $end
$scope begin adder_chain[8] $end
$var parameter 5 ] i $end
$scope module fa $end
$var wire 1 ^ a $end
$var wire 1 _ b $end
$var wire 1 ` cin $end
$var wire 1 a cout $end
$var wire 1 b sum $end
$upscope $end
$upscope $end
$scope begin adder_chain[9] $end
$var parameter 5 c i $end
$scope module fa $end
$var wire 1 d a $end
$var wire 1 e b $end
$var wire 1 f cin $end
$var wire 1 g cout $end
$var wire 1 h sum $end
$upscope $end
$upscope $end
$scope begin adder_chain[10] $end
$var parameter 5 i i $end
$scope module fa $end
$var wire 1 j a $end
$var wire 1 k b $end
$var wire 1 l cin $end
$var wire 1 m cout $end
$var wire 1 n sum $end
$upscope $end
$upscope $end
$scope begin adder_chain[11] $end
$var parameter 5 o i $end
$scope module fa $end
$var wire 1 p a $end
$var wire 1 q b $end
$var wire 1 r cin $end
$var wire 1 s cout $end
$var wire 1 t sum $end
$upscope $end
$upscope $end
$scope begin adder_chain[12] $end
$var parameter 5 u i $end
$scope module fa $end
$var wire 1 v a $end
$var wire 1 w b $end
$var wire 1 x cin $end
$var wire 1 y cout $end
$var wire 1 z sum $end
$upscope $end
$upscope $end
$scope begin adder_chain[13] $end
$var parameter 5 { i $end
$scope module fa $end
$var wire 1 | a $end
$var wire 1 } b $end
$var wire 1 ~ cin $end
$var wire 1 !" cout $end
$var wire 1 "" sum $end
$upscope $end
$upscope $end
$scope begin adder_chain[14] $end
$var parameter 5 #" i $end
$scope module fa $end
$var wire 1 $" a $end
$var wire 1 %" b $end
$var wire 1 &" cin $end
$var wire 1 '" cout $end
$var wire 1 (" sum $end
$upscope $end
$upscope $end
$scope begin adder_chain[15] $end
$var parameter 5 )" i $end
$scope module fa $end
$var wire 1 *" a $end
$var wire 1 +" b $end
$var wire 1 ," cin $end
$var wire 1 -" cout $end
$var wire 1 ." sum $end
$upscope $end
$upscope $end
$scope begin adder_chain[16] $end
$var parameter 6 /" i $end
$scope module fa $end
$var wire 1 0" a $end
$var wire 1 1" b $end
$var wire 1 2" cin $end
$var wire 1 3" cout $end
$var wire 1 4" sum $end
$upscope $end
$upscope $end
$scope begin adder_chain[17] $end
$var parameter 6 5" i $end
$scope module fa $end
$var wire 1 6" a $end
$var wire 1 7" b $end
$var wire 1 8" cin $end
$var wire 1 9" cout $end
$var wire 1 :" sum $end
$upscope $end
$upscope $end
$scope begin adder_chain[18] $end
$var parameter 6 ;" i $end
$scope module fa $end
$var wire 1 <" a $end
$var wire 1 =" b $end
$var wire 1 >" cin $end
$var wire 1 ?" cout $end
$var wire 1 @" sum $end
$upscope $end
$upscope $end
$scope begin adder_chain[19] $end
$var parameter 6 A" i $end
$scope module fa $end
$var wire 1 B" a $end
$var wire 1 C" b $end
$var wire 1 D" cin $end
$var wire 1 E" cout $end
$var wire 1 F" sum $end
$upscope $end
$upscope $end
$scope begin adder_chain[20] $end
$var parameter 6 G" i $end
$scope module fa $end
$var wire 1 H" a $end
$var wire 1 I" b $end
$var wire 1 J" cin $end
$var wire 1 K" cout $end
$var wire 1 L" sum $end
$upscope $end
$upscope $end
$scope begin adder_chain[21] $end
$var parameter 6 M" i $end
$scope module fa $end
$var wire 1 N" a $end
$var wire 1 O" b $end
$var wire 1 P" cin $end
$var wire 1 Q" cout $end
$var wire 1 R" sum $end
$upscope $end
$upscope $end
$scope begin adder_chain[22] $end
$var parameter 6 S" i $end
$scope module fa $end
$var wire 1 T" a $end
$var wire 1 U" b $end
$var wire 1 V" cin $end
$var wire 1 W" cout $end
$var wire 1 X" sum $end
$upscope $end
$upscope $end
$scope begin adder_chain[23] $end
$var parameter 6 Y" i $end
$scope module fa $end
$var wire 1 Z" a $end
$var wire 1 [" b $end
$var wire 1 \" cin $end
$var wire 1 ]" cout $end
$var wire 1 ^" sum $end
$upscope $end
$upscope $end
$scope begin adder_chain[24] $end
$var parameter 6 _" i $end
$scope module fa $end
$var wire 1 `" a $end
$var wire 1 a" b $end
$var wire 1 b" cin $end
$var wire 1 c" cout $end
$var wire 1 d" sum $end
$upscope $end
$upscope $end
$scope begin adder_chain[25] $end
$var parameter 6 e" i $end
$scope module fa $end
$var wire 1 f" a $end
$var wire 1 g" b $end
$var wire 1 h" cin $end
$var wire 1 i" cout $end
$var wire 1 j" sum $end
$upscope $end
$upscope $end
$scope begin adder_chain[26] $end
$var parameter 6 k" i $end
$scope module fa $end
$var wire 1 l" a $end
$var wire 1 m" b $end
$var wire 1 n" cin $end
$var wire 1 o" cout $end
$var wire 1 p" sum $end
$upscope $end
$upscope $end
$scope begin adder_chain[27] $end
$var parameter 6 q" i $end
$scope module fa $end
$var wire 1 r" a $end
$var wire 1 s" b $end
$var wire 1 t" cin $end
$var wire 1 u" cout $end
$var wire 1 v" sum $end
$upscope $end
$upscope $end
$scope begin adder_chain[28] $end
$var parameter 6 w" i $end
$scope module fa $end
$var wire 1 x" a $end
$var wire 1 y" b $end
$var wire 1 z" cin $end
$var wire 1 {" cout $end
$var wire 1 |" sum $end
$upscope $end
$upscope $end
$scope begin adder_chain[29] $end
$var parameter 6 }" i $end
$scope module fa $end
$var wire 1 ~" a $end
$var wire 1 !# b $end
$var wire 1 "# cin $end
$var wire 1 ## cout $end
$var wire 1 $# sum $end
$upscope $end
$upscope $end
$scope begin adder_chain[30] $end
$var parameter 6 %# i $end
$scope module fa $end
$var wire 1 &# a $end
$var wire 1 '# b $end
$var wire 1 (# cin $end
$var wire 1 )# cout $end
$var wire 1 *# sum $end
$upscope $end
$upscope $end
$scope begin adder_chain[31] $end
$var parameter 6 +# i $end
$scope module fa $end
$var wire 1 ,# a $end
$var wire 1 -# b $end
$var wire 1 .# cin $end
$var wire 1 /# cout $end
$var wire 1 0# sum $end
$upscope $end
$upscope $end
$upscope $end
$scope begin $ivl_for_loop0 $end
$var integer 32 1# i [31:0] $end
$upscope $end
$scope task check $end
$upscope $end
$upscope $end
$enddefinitions $end
$comment Show the parameter values. $end
$dumpall
b11111 +#
b11110 %#
b11101 }"
b11100 w"
b11011 q"
b11010 k"
b11001 e"
b11000 _"
b10111 Y"
b10110 S"
b10101 M"
b10100 G"
b10011 A"
b10010 ;"
b10001 5"
b10000 /"
b1111 )"
b1110 #"
b1101 {
b1100 u
b1011 o
b1010 i
b1001 c
b1000 ]
b111 W
b110 Q
b101 K
b100 E
b11 ?
b10 9
b1 3
b0 -
b100000 ,
b100000 #
$end
#0
$dumpvars
b0 1#
00#
0/#
0.#
0-#
0,#
0*#
0)#
0(#
0'#
0&#
0$#
0##
0"#
0!#
0~"
0|"
0{"
0z"
0y"
0x"
0v"
0u"
0t"
0s"
0r"
0p"
0o"
0n"
0m"
0l"
0j"
0i"
0h"
0g"
0f"
0d"
0c"
0b"
0a"
0`"
0^"
0]"
0\"
0["
0Z"
0X"
0W"
0V"
0U"
0T"
0R"
0Q"
0P"
0O"
0N"
0L"
0K"
0J"
0I"
0H"
0F"
0E"
0D"
0C"
0B"
0@"
0?"
0>"
0="
0<"
0:"
09"
08"
07"
06"
04"
03"
02"
01"
00"
0."
0-"
0,"
0+"
0*"
0("
0'"
0&"
0%"
0$"
0""
0!"
0~
0}
0|
0z
0y
0x
0w
0v
0t
0s
0r
0q
0p
0n
0m
0l
0k
0j
0h
0g
0f
0e
0d
0b
0a
0`
0_
0^
0\
0[
0Z
0Y
0X
0V
0U
0T
0S
0R
0P
0O
0N
0M
0L
0J
0I
0H
0G
0F
0D
0C
0B
0A
0@
0>
0=
0<
0;
0:
08
07
06
05
04
02
01
00
0/
0.
b0 +
b0 *
b0 )
b0 (
bx '
0&
b0 %
b0 $
0"
b0 !
$end
#10
b0 '
#15
18
1>
1D
1J
1P
1V
1\
1b
1h
1n
1t
1z
1""
1("
1."
14"
1:"
1@"
1F"
1L"
1R"
1X"
1^"
1d"
1j"
1p"
1v"
1|"
1$#
1*#
b11111111111111111111111111111110 !
b11111111111111111111111111111110 *
10#
16
1<
1B
1H
1N
1T
1Z
1`
1f
1l
1r
1x
1~
1&"
1,"
12"
18"
1>"
1D"
1J"
1P"
1V"
1\"
1b"
1h"
1n"
1t"
1z"
1"#
1(#
1.#
1"
11
17
1=
1C
1I
1O
1U
1[
1a
1g
1m
1s
1y
1!"
1'"
1-"
13"
19"
1?"
1E"
1K"
1Q"
1W"
1]"
1c"
1i"
1o"
1u"
1{"
1##
1)#
b111111111111111111111111111111110 +
1/#
1/
15
1;
1A
1G
1M
1S
1Y
1_
1e
1k
1q
1w
1}
1%"
1+"
11"
17"
1="
1C"
1I"
1O"
1U"
1["
1a"
1g"
1m"
1s"
1y"
1!#
1'#
1-#
1.
14
1:
1@
1F
1L
1R
1X
1^
1d
1j
1p
1v
1|
1$"
1*"
10"
16"
1<"
1B"
1H"
1N"
1T"
1Z"
1`"
1f"
1l"
1r"
1x"
1~"
1&#
1,#
b11111111111111111111111111111111 %
b11111111111111111111111111111111 )
b11111111111111111111111111111111 $
b11111111111111111111111111111111 (
#25
b111111111111111111111111111111110 '
#30
1"
1/#
10#
1.#
1)#
1*#
1(#
1##
1$#
1"#
1{"
1|"
1z"
1u"
1v"
1t"
1o"
1p"
1n"
1i"
1j"
1h"
1c"
1d"
1b"
1]"
1^"
1\"
1W"
1X"
1V"
1Q"
1R"
1P"
1K"
1L"
1J"
1E"
1F"
1D"
1?"
1@"
1>"
19"
1:"
18"
13"
14"
12"
1-"
1."
1,"
1'"
1("
1&"
1!"
1""
1~
1y
1z
1x
1s
1t
1r
1m
1n
1l
1g
1h
1f
1a
1b
1`
1[
1\
1Z
1U
1V
1T
1O
1P
1N
1I
1J
1H
1C
1D
1B
1=
1>
1<
17
18
16
11
b11111111111111111111111111111111 !
b11111111111111111111111111111111 *
12
10
b111111111111111111111111111111111 +
1&
#40
b111111111111111111111111111111111 '
#45
1~
1y
1z
1x
1s
1r
1m
0n
1."
1:"
0d"
0`
0l
1,"
18"
0J"
0b"
0.#
0[
0g
1'"
13"
0E"
0]"
0)#
08
0D
0J
0V
04"
0R"
0X"
0p"
0v"
0$#
06
0<
0B
0H
0N
0T
0Z
0f
1&"
02"
0>"
0D"
0P"
0V"
0\"
0h"
0n"
0t"
0z"
0"#
0(#
0"
01
07
1>
0=
0C
0I
1P
0O
0U
1b
0a
0""
1!"
0-"
09"
1@"
0?"
1L"
0K"
0Q"
0W"
0c"
1j"
0i"
0o"
0u"
1|"
0{"
0##
10#
0/#
1\
1h
0t
0("
1F"
1^"
b11010010100111101001001110100101 !
b11010010100111101001001110100101 *
1*#
00
05
0;
0A
0G
0M
0S
0_
0}
0+"
07"
0="
0I"
0O"
0U"
0a"
0g"
0m"
0s"
0y"
0!#
0-#
0.
04
0@
0F
0R
0X
0d
0p
0$"
0*"
06"
0B"
0N"
0T"
0Z"
0`"
0l"
0r"
0~"
0&#
b101111100000000000 +
0&
b1000000100010010101111010000001 %
b1000000100010010101111010000001 )
b10010010000101010011010100100100 $
b10010010000101010011010100100100 (
#55
b11010010100111101001001110100101 '
#60
1."
1,"
1'"
1v"
1J
1t"
1H
1&"
1o"
1C
1!"
0""
1n"
1B
1~
1i"
1=
1y
0j"
0>
1z
1\"
1h"
1<
1x
1W"
1c"
17
1s
0t
1R"
0:"
1r
1P"
1l
08"
1V"
1b"
16
1m
1K"
1g
03"
1Q"
1]"
11
0D
0\
0n
0L"
0p"
0*#
08
1V
0h
1("
14"
0@"
0X"
1^"
0d"
b10111000101010011101000101110001 !
b10111000101010011101000101110001 *
1$#
10
1;
1A
0Y
1_
0k
1}
1I"
1O"
1g"
1m"
0'#
1-#
1.
14
0:
1R
0^
1d
0|
1$"
00"
0<"
1N"
1T"
1Z"
1`"
0f"
1~"
0,#
b1111111000001111110000011111 +
1&
b10000110101110010111101100001101 %
b10000110101110010111101100001101 )
b110001111100000101011001100011 $
b110001111100000101011001100011 (
b1 1#
#70
b10111000101010011101000101110001 '
#75
0\
0*#
0Z
0(#
0\"
1B
0U
0n"
0##
0W"
1=
0i"
1V
1$#
0r
0:"
1X"
0>
0T
1j"
0"#
0m
08"
1D"
0V"
1<
0O
0~
0,"
0h"
0{"
03"
1?"
0Q"
17
0y
0'"
0c"
1n
14"
08
1P
1d"
1|"
0l
02"
1>"
0P"
16
0H
0N
0x
0&"
0b"
0t"
0z"
0g
0-"
19"
0K"
02
11
1D
0C
1J
0I
0b
0t
0s
0""
0!"
0@"
1F"
1^"
0]"
0p"
0o"
1v"
b11000000000000001111 +
0u"
00#
1h
1z
1("
1."
1L"
b111011111110011101011001111000 !
b111011111110011101011001111000 *
1R"
0/
15
0;
0A
1G
0_
0q
0}
17"
1="
0C"
0["
1a"
0g"
0m"
1s"
0-#
04
1:
0d
0v
0$"
1*"
16"
0H"
0N"
0`"
1f"
b1001001101110101001000010010 %
b1001001101110101001000010010 )
b110010110000101000010001100101 $
b110010110000101000010001100101 (
b10 1#
#85
b111011111110011101011001111000 '
#90
1*#
1(#
1##
0$#
1"#
1\
1{"
1Z
0|"
1U
1F"
1z"
0V
1D"
1u"
1T
1?"
0v"
1O
1t"
0P
0@"
1o"
1N
1>"
1I
19"
0J
1:"
12"
1n"
1H
1f
1,"
18"
1"
1B
1-"
1i"
1C
1a
1'"
13"
1/#
1>
b101111100000011111000001011111111 +
1=
1h
1""
1."
0j"
0D
1t
0("
14"
b1000001111110111011111010000100 !
b1000001111110111011111010000100 *
0p"
1;
1M
1S
1_
0e
1}
1+"
0="
0I"
1g"
1y"
1!#
1-#
1@
0L
0R
1^
1p
1$"
10"
1<"
1H"
1l"
0x"
0~"
1,#
b10111011001000111111000101110110 %
b10111011001000111111000101110110 )
b10000110110101111100110100001101 $
b10000110110101111100110100001101 (
b11 1#
#100
b101000001111110111011111010000100 '
#105
1b"
1]"
1:"
18"
0^"
13"
1\"
1W"
12"
0\
0*#
1-"
0Z
0X"
0(#
0U
1V"
0##
1,"
1Q"
1'"
1V
0R"
1$#
1("
0T
1h
1P"
0"#
1&"
1B
0O
1f
1K"
0{"
1"
1!"
1=
1a
1/#
0""
0>
1P
1b
1r
0L"
1|"
10#
1~
0<
1H
0N
1`
1l
1m
0>"
1D"
1J"
1t"
0z"
1.#
1y
18
07
1D
1C
1J
0I
1[
1g
1n
09"
0@"
1?"
0F"
1E"
1d"
1p"
1o"
1v"
0u"
b110001101111110111110111100011011 +
1)#
1t
0z
0."
b10111101000000100100111101111010 !
b10111101000000100100111101111010 *
04"
05
1A
0G
0M
0S
1Y
1e
1k
07"
1="
1C"
0a"
1m"
0s"
0y"
0!#
1'#
1L
1R
1X
1d
0p
1v
0*"
00"
06"
1x"
1~"
1&#
b11000110001011011111011110001100 %
b11000110001011011111011110001100 )
b11110110110101000101011111101101 $
b11110110110101000101011111101101 (
b100 1#
#115
b110111101000000100100111101111010 '
#120
1b"
1]"
1:"
0^"
18"
1\"
0("
1b
13"
1W"
10#
1D
0&"
1p"
1`
1t
0X"
1.#
1B
0!"
1n"
1[
1r
02"
1D"
1V"
1)#
1=
1i"
1\
1m
0-"
1?"
1Q"
1*#
0>
1""
1j"
0J
1Z
0h
0n
1."
1@"
0v"
1(#
06
0<
0~
1h"
0H
1U
0f
0l
0,"
1>"
0J"
1P"
0t"
1##
0"
01
07
0y
1c"
0C
0V
0a
0g
0'"
19"
1F"
0E"
0L"
1K"
0o"
0$#
0/#
18
0P
04"
1R"
0d"
0|"
b11000110001011101010100110001011 !
b11000110001011101010100110001011 *
12
00
1/
0A
1S
0_
0e
0w
0}
0%"
17"
0C"
1I"
1U"
1["
0m"
1!#
0-#
0.
14
0@
0L
0^
0d
0v
1|
0$"
10"
16"
1N"
0T"
0Z"
1`"
0l"
0x"
0,#
b11000111111011100000100110001000 +
0&
b1100010111101111000010011000101 %
b1100010111101111000010011000101 )
b1100011001101110010010011000110 $
b1100011001101110010010011000110 (
b101 1#
#130
b11000110001011101010100110001011 '
#135
1p"
1n"
1i"
1j"
1h"
1c"
1D
0d"
1B
1b"
1=
1]"
1>
12"
1>"
1<
1Z
1-"
1(#
19"
1\"
17
1U
1##
1t
1("
1:"
1W"
08
1V
1h
0."
1$#
1r
1&"
18"
0X"
16
1T
1f
1l
1~
1,"
1J"
1P"
1"#
1"
1`
1m
1!"
13"
1D"
1V"
1.#
11
1O
1a
1g
1y
1'"
1E"
1K"
1{"
1/#
1J
0\
1[
0n
1""
04"
0@"
1?"
0R"
1Q"
1v"
0*#
b111100111111111111110111111001110 +
1)#
02
0b
0F"
0L"
1^"
b101110100000100110101001011100 !
b101110100000100110101001011100 *
00#
15
1G
1M
0Y
1e
0k
1w
1}
1%"
0+"
01"
0="
0O"
1a"
1s"
1y"
0'#
1.
04
1L
1^
1d
1v
1$"
1*"
1B"
0H"
1Z"
0`"
1x"
1,#
b111011110100100111001001110111 %
b111011110100100111001001110111 )
b11110010101011111111011111100101 $
b11110010101011111111011111100101 (
b110 1#
#145
b100101110100000100110101001011100 '
#150
12"
0P"
1-"
0K"
1L"
0."
0J"
1,"
0E"
1'"
1("
1F"
1<
1&"
0D"
1\"
1N
1Z
1z"
1(#
17
1!"
0?"
1W"
1h"
1I
1U
1u"
1##
1c"
0J
0t
0:"
0v"
06
1~
1@"
0X"
1H
1T
0r
08"
1t"
1"#
01
1B
1`
1f
1l
1x
1y
0>"
1V"
1b"
1n"
1.#
1"
1C
1O
0m
03"
1o"
1{"
12
0>
1=
1\
1[
1b
1a
0h
1g
1s
0z
09"
0R"
1Q"
0^"
1]"
0j"
1i"
1*#
1)#
10#
b111111111110000011111011111111100 +
1/#
08
0D
0P
0V
1n
0""
14"
1d"
0p"
0|"
b11000001000111010100010110000001 !
b11000001000111010100010110000001 *
0$#
0/
0;
1Y
1_
0e
1q
0w
07"
1O"
0U"
0["
0g"
1'#
1-#
14
1@
0L
0R
0j
1p
0|
00"
06"
1T"
1`"
1l"
0x"
0~"
b11111001001100000110100111110010 %
b11111001001100000110100111110010 )
b11000111111011001101101110001111 $
b11000111111011001101101110001111 (
b111 1#
#160
b111000001000111010100010110000001 '
#165
1,"
1'"
1("
1b
1&"
10#
1`
1!"
1.#
1[
1)#
1\
0""
1*#
0H
0d"
1Z
1~
0t"
1(#
0C
0b"
1U
1y
0o"
1##
0]"
1D
1^"
0T
0z
1p"
0"#
0B
0\"
0O
1x
0n"
0{"
0=
0W"
1s
0i"
1>
04"
1X"
18
1P
1t
1j"
1|"
0<
02"
0V"
16
0N
0f
1l
1r
0h"
0z"
0"
07
0-"
0Q"
11
0J
0I
0a
0h
1g
0n
1m
1:"
0L"
0c"
0v"
0u"
0/#
0V
1."
0@"
0$#
b11010110110010101100100110101110 !
b11010110110010101100100110101110 *
02
10
1/
05
1;
0G
0M
0_
1e
1k
0}
17"
1C"
0I"
0O"
1U"
1["
0a"
1g"
0s"
0y"
0-#
0.
04
0:
1L
1R
0^
1|
0*"
0<"
0B"
0N"
0T"
0Z"
0`"
0f"
1x"
1~"
0,#
b11000000000000001111110110000011 +
1&
b1100010110010100100111011000101 %
b1100010110010100100111011000101 )
b1110100000000000111101011101000 $
b1110100000000000111101011101000 (
b1000 1#
#175
b11010110110010101100100110101110 '
#180
1."
1,"
1'"
1&"
1!"
0""
1~
1N
1y
1z"
1D"
1I
0z
1u"
1?"
1x
1V
1s
1$#
1L"
1d"
1H
1T
0b
0t
1t"
1"#
00#
1B
0Z
0l
1>"
1J"
1b"
1n"
0(#
1C
1O
0`
0r
1o"
1{"
0.#
1=
0U
0g
19"
1E"
1]"
1i"
0##
1D
1P
1\
0[
0n
0m
14"
1R"
0X"
1p"
1|"
1*#
0)#
0>
0J
0("
0:"
0@"
1F"
0^"
0j"
b1110101001110011000000011101010 !
b1110101001110011000000011101010 *
0v"
00
1A
1M
0S
0Y
0e
0k
1w
11"
1O"
0U"
1m"
1y"
0!#
0'#
1.
1:
1F
0R
0d
0v
0$"
16"
1<"
1B"
1Z"
1f"
1r"
0~"
b111101000111001111000001111010 +
0&
b10110101010110101100000101101 %
b10110101010110101100000101101 )
b1011110100011100010100010111101 $
b1011110100011100010100010111101 (
b1001 1#
#190
b1110101001110011000000011101010 '
#195
0,"
1D"
0'"
1?"
1("
1t
0@"
0&"
0H
1r
1>"
0t"
0!"
0C
1m
19"
0o"
08
1d"
1:"
1X"
06
1>
1""
1b"
1j"
0B
0N
0Z
1l
0x
18"
1V"
1\"
0n"
0z"
0(#
01
1<
0T
0~
02"
1J"
1P"
1]"
1h"
0"#
0=
0I
0U
1g
0s
13"
1Q"
1W"
0i"
0u"
0##
12
17
1P
0O
1b
0n
0z
0y
1."
0-"
0F"
1E"
0L"
1K"
0^"
1c"
1|"
b11111111100000110000000100 +
0{"
10#
1D
0J
1V
0\
04"
1R"
1p"
0v"
1$#
b10110111011000101110100101101101 !
b10110111011000101110100101101101 *
0*#
0/
15
0;
0M
1_
1e
1k
0q
0w
0%"
1+"
0C"
1I"
1U"
0["
1a"
0g"
0y"
1-#
14
0:
0@
0F
1R
0X
1d
0p
1$"
10"
1N"
1T"
1`"
0f"
0l"
0r"
1~"
0&#
b10000101011100111000011100001010 %
b10000101011100111000011100001010 )
b110001111011110110001001100011 $
b110001111011110110001001100011 (
b1010 1#
#205
b10110111011000101110100101101101 '
#210
1\"
1W"
1X"
1V"
1Q"
0R"
0P"
0K"
1L"
0J"
0E"
1F"
0t
0j"
0D"
0r
0h"
0?"
0m
0c"
0>
1h
1n
0:"
1T
1@"
1"#
0<
1f
0l
08"
0b"
1"
1O
0>"
1{"
07
1a
0g
03"
0]"
1/#
0P
1\
0."
b100100000110000000000001001000000 +
09"
0|"
1*#
02
18
1V
0b
1^"
1d"
1$#
b1100101110111000110011011001010 !
b1100101110111000110011011001010 *
00#
1M
1Y
0e
1%"
0+"
01"
07"
1C"
1y"
1'#
0.
04
0R
1^
0d
0$"
00"
06"
0B"
0Z"
0`"
0~"
1,#
b11010101011110000100010110101010 %
b11010101011110000100010110101010 )
b10010000011001000010000100100000 $
b10010000011001000010000100100000 (
b1011 1#
#220
b101100101110111000110011011001010 '
#225
0t
1B
0r
1n"
1=
0m
1i"
0X"
1P
0V
1n
1z
1|"
0$#
1&"
0V"
1<
1N
0T
0f
0l
1x
1~
1h"
1z"
0"#
0"
1!"
0Q"
0\"
0b"
17
1I
0O
0a
0g
1s
1y
1c"
1u"
0{"
0/#
12
1D
1""
1("
1."
14"
1:"
0F"
0L"
1R"
0W"
1^"
b10110000000000111000000101100 +
0]"
1p"
08
0>
1h
0@"
0d"
b1010100101000111111011010101001 !
b1010100101000111111011010101001 *
0j"
1/
0A
1G
0M
0Y
0_
0k
1q
1w
1}
0%"
1+"
11"
17"
0C"
0I"
0O"
0U"
1["
0m"
1s"
0y"
0'#
0-#
14
1:
1F
0L
1X
0^
1d
1j
1p
1v
0<"
0T"
1`"
1f"
1r"
0x"
1&#
0,#
b1001100000111011100000010011 %
b1001100000111011100000010011 )
b1001011001000000011111010010110 $
b1001011001000000011111010010110 (
b1100 1#
#235
b1010100101000111111011010101001 '
#240
1X"
1V"
1Q"
0R"
1P"
1K"
1""
1<
1~
1J"
1h"
17
1y
1E"
1c"
18
1z
1@"
1d"
0N
0V
1r
0("
0z"
0$#
16
0B
1Z
1x
12"
18"
1>"
1D"
1b"
0n"
1(#
0H
0I
0T
1m
0&"
1,"
0t"
0u"
0"#
11
0=
1U
1s
1-"
13"
19"
1?"
1]"
0i"
1##
1D
0C
1J
1P
0O
1b
0n
0!"
1'"
0F"
0L"
1p"
0o"
1v"
1|"
b1000011011111111011100010000110 +
0{"
10#
02
1>
1\
0t
1."
14"
1:"
0^"
1j"
b11011111010001111011001110111110 !
b11011111010001111011001110111110 *
1*#
1A
0G
1M
1S
1_
1k
0}
1%"
1="
1C"
1I"
1m"
0s"
1y"
1!#
1-#
1.
0:
1R
0X
0p
0|
1$"
1*"
10"
16"
1<"
1Z"
0f"
1~"
0&#
b10110101100111111101110101101011 %
b10110101100111111101110101101011 )
b101001101001111101011001010011 $
b101001101001111101011001010011 (
b1101 1#
#250
b11011111010001111011001110111110 '
#255
1~
1D"
1y
1?"
1@"
1<
1x
1h"
1H
1>"
1P"
1t"
17
1s
1c"
1C
1."
19"
1K"
1o"
08
0d"
0D
1l
1,"
0:"
0^"
0p"
06
0Z
1r
0V"
0b"
0(#
1B
0`
1g
1&"
1'"
02"
08"
0J"
0\"
1n"
0.#
01
0U
1m
0Q"
0]"
0##
0>
1=
1\
0[
0b
0h
0""
1!"
0("
0-"
14"
03"
1F"
0E"
1X"
0W"
0j"
1i"
1*#
0)#
00#
1J
0n
1t
0z
0L"
1R"
1v"
b1011000011011011000100010110001 !
b1011000011011011000100010110001 *
12
10
0/
1;
0S
1Y
0_
1e
1}
0%"
0+"
01"
0C"
1U"
0["
1g"
0!#
1'#
0-#
0.
0F
0R
0j
1p
0v
0*"
1H"
0N"
0Z"
0r"
0~"
b1110001011001111110000011101 +
1&
b1010111010101100011111010101110 %
b1010111010101100011111010101110 )
b1000101110100101000000010 $
b1000101110100101000000010 (
b1110 1#
#265
b1011000011011011000100010110001 '
